// class version 50.0 (50)
// access flags 0x421
public abstract class net/minecraft/client/gui/inventory/GuiContainer extends net/minecraft/client/gui/GuiScreen  {

  // compiled from: GuiContainer.java

  @Lnet/minecraftforge/fml/relauncher/SideOnly;(value=Lnet/minecraftforge/fml/relauncher/Side;.CLIENT)

  // access flags 0x19
  public final static Lnet/minecraft/util/ResourceLocation; INVENTORY_BACKGROUND

  // access flags 0x4
  protected I xSize

  // access flags 0x4
  protected I ySize

  // access flags 0x1
  public Lnet/minecraft/inventory/Container; inventorySlots

  // access flags 0x4
  protected I guiLeft

  // access flags 0x4
  protected I guiTop

  // access flags 0x2
  private Lnet/minecraft/inventory/Slot; theSlot

  // access flags 0x2
  private Lnet/minecraft/inventory/Slot; clickedSlot

  // access flags 0x2
  private Z isRightMouseClick

  // access flags 0x2
  private Lnet/minecraft/item/ItemStack; draggedStack

  // access flags 0x2
  private I touchUpX

  // access flags 0x2
  private I touchUpY

  // access flags 0x2
  private Lnet/minecraft/inventory/Slot; returningStackDestSlot

  // access flags 0x2
  private J returningStackTime

  // access flags 0x2
  private Lnet/minecraft/item/ItemStack; returningStack

  // access flags 0x2
  private Lnet/minecraft/inventory/Slot; currentDragTargetSlot

  // access flags 0x2
  private J dragItemDropDelay

  // access flags 0x14
  // signature Ljava/util/Set<Lnet/minecraft/inventory/Slot;>;
  // declaration: java.util.Set<net.minecraft.inventory.Slot>
  protected final Ljava/util/Set; dragSplittingSlots

  // access flags 0x4
  protected Z dragSplitting

  // access flags 0x2
  private I dragSplittingLimit

  // access flags 0x2
  private I dragSplittingButton

  // access flags 0x2
  private Z ignoreMouseUp

  // access flags 0x2
  private I dragSplittingRemnant

  // access flags 0x2
  private J lastClickTime

  // access flags 0x2
  private Lnet/minecraft/inventory/Slot; lastClickSlot

  // access flags 0x2
  private I lastClickButton

  // access flags 0x2
  private Z doubleClick

  // access flags 0x2
  private Lnet/minecraft/item/ItemStack; shiftClickedSlot

  // access flags 0x1
  public <init>(Lnet/minecraft/inventory/Container;)V
   L0
    LINENUMBER 69 L0
    ALOAD 0
    INVOKESPECIAL net/minecraft/client/gui/GuiScreen.<init> ()V
   L1
    LINENUMBER 31 L1
    ALOAD 0
    SIPUSH 176
    PUTFIELD net/minecraft/client/gui/inventory/GuiContainer.xSize : I
   L2
    LINENUMBER 33 L2
    ALOAD 0
    SIPUSH 166
    PUTFIELD net/minecraft/client/gui/inventory/GuiContainer.ySize : I
   L3
    LINENUMBER 47 L3
    ALOAD 0
    GETSTATIC net/minecraft/item/ItemStack.EMPTY : Lnet/minecraft/item/ItemStack;
    PUTFIELD net/minecraft/client/gui/inventory/GuiContainer.draggedStack : Lnet/minecraft/item/ItemStack;
   L4
    LINENUMBER 53 L4
    ALOAD 0
    GETSTATIC net/minecraft/item/ItemStack.EMPTY : Lnet/minecraft/item/ItemStack;
    PUTFIELD net/minecraft/client/gui/inventory/GuiContainer.returningStack : Lnet/minecraft/item/ItemStack;
   L5
    LINENUMBER 56 L5
    ALOAD 0
    INVOKESTATIC com/google/common/collect/Sets.newHashSet ()Ljava/util/HashSet;
    PUTFIELD net/minecraft/client/gui/inventory/GuiContainer.dragSplittingSlots : Ljava/util/Set;
   L6
    LINENUMBER 66 L6
    ALOAD 0
    GETSTATIC net/minecraft/item/ItemStack.EMPTY : Lnet/minecraft/item/ItemStack;
    PUTFIELD net/minecraft/client/gui/inventory/GuiContainer.shiftClickedSlot : Lnet/minecraft/item/ItemStack;
   L7
    LINENUMBER 70 L7
    ALOAD 0
    ALOAD 1
    PUTFIELD net/minecraft/client/gui/inventory/GuiContainer.inventorySlots : Lnet/minecraft/inventory/Container;
   L8
    LINENUMBER 71 L8
    ALOAD 0
    ICONST_1
    PUTFIELD net/minecraft/client/gui/inventory/GuiContainer.ignoreMouseUp : Z
   L9
    LINENUMBER 72 L9
    RETURN
   L10
    LOCALVARIABLE this Lnet/minecraft/client/gui/inventory/GuiContainer; L0 L10 0
    LOCALVARIABLE inventorySlotsIn Lnet/minecraft/inventory/Container; L0 L10 1
    MAXSTACK = 2
    MAXLOCALS = 2

  // access flags 0x1
  public initGui()V
   L0
    LINENUMBER 80 L0
    ALOAD 0
    INVOKESPECIAL net/minecraft/client/gui/GuiScreen.initGui ()V
   L1
    LINENUMBER 81 L1
    ALOAD 0
    GETFIELD net/minecraft/client/gui/inventory/GuiContainer.mc : Lnet/minecraft/client/Minecraft;
    GETFIELD net/minecraft/client/Minecraft.player : Lnet/minecraft/client/entity/EntityPlayerSP;
    ALOAD 0
    GETFIELD net/minecraft/client/gui/inventory/GuiContainer.inventorySlots : Lnet/minecraft/inventory/Container;
    PUTFIELD net/minecraft/client/entity/EntityPlayerSP.openContainer : Lnet/minecraft/inventory/Container;
   L2
    LINENUMBER 82 L2
    ALOAD 0
    ALOAD 0
    GETFIELD net/minecraft/client/gui/inventory/GuiContainer.width : I
    ALOAD 0
    GETFIELD net/minecraft/client/gui/inventory/GuiContainer.xSize : I
    ISUB
    ICONST_2
    IDIV
    PUTFIELD net/minecraft/client/gui/inventory/GuiContainer.guiLeft : I
   L3
    LINENUMBER 83 L3
    ALOAD 0
    ALOAD 0
    GETFIELD net/minecraft/client/gui/inventory/GuiContainer.height : I
    ALOAD 0
    GETFIELD net/minecraft/client/gui/inventory/GuiContainer.ySize : I
    ISUB
    ICONST_2
    IDIV
    PUTFIELD net/minecraft/client/gui/inventory/GuiContainer.guiTop : I
   L4
    LINENUMBER 84 L4
    RETURN
   L5
    LOCALVARIABLE this Lnet/minecraft/client/gui/inventory/GuiContainer; L0 L5 0
    MAXSTACK = 3
    MAXLOCALS = 1

  // access flags 0x1
  public drawScreen(IIF)V
   L0
    LINENUMBER 91 L0
    ALOAD 0
    INVOKEVIRTUAL net/minecraft/client/gui/inventory/GuiContainer.drawDefaultBackground ()V
   L1
    LINENUMBER 92 L1
    ALOAD 0
    GETFIELD net/minecraft/client/gui/inventory/GuiContainer.guiLeft : I
    ISTORE 4
   L2
    LINENUMBER 93 L2
    ALOAD 0
    GETFIELD net/minecraft/client/gui/inventory/GuiContainer.guiTop : I
    ISTORE 5
   L3
    LINENUMBER 94 L3
    ALOAD 0
    FLOAD 3
    ILOAD 1
    ILOAD 2
    INVOKEVIRTUAL net/minecraft/client/gui/inventory/GuiContainer.drawGuiContainerBackgroundLayer (FII)V
   L4
    LINENUMBER 95 L4
    INVOKESTATIC net/minecraft/client/renderer/GlStateManager.disableRescaleNormal ()V
   L5
    LINENUMBER 96 L5
    INVOKESTATIC net/minecraft/client/renderer/RenderHelper.disableStandardItemLighting ()V
   L6
    LINENUMBER 97 L6
    INVOKESTATIC net/minecraft/client/renderer/GlStateManager.disableLighting ()V
   L7
    LINENUMBER 98 L7
    INVOKESTATIC net/minecraft/client/renderer/GlStateManager.disableDepth ()V
   L8
    LINENUMBER 99 L8
    ALOAD 0
    ILOAD 1
    ILOAD 2
    FLOAD 3
    INVOKESPECIAL net/minecraft/client/gui/GuiScreen.drawScreen (IIF)V
   L9
    LINENUMBER 100 L9
    INVOKESTATIC net/minecraft/client/renderer/RenderHelper.enableGUIStandardItemLighting ()V
   L10
    LINENUMBER 101 L10
    INVOKESTATIC net/minecraft/client/renderer/GlStateManager.pushMatrix ()V
   L11
    LINENUMBER 102 L11
    ILOAD 4
    I2F
    ILOAD 5
    I2F
    FCONST_0
    INVOKESTATIC net/minecraft/client/renderer/GlStateManager.translate (FFF)V
   L12
    LINENUMBER 103 L12
    FCONST_1
    FCONST_1
    FCONST_1
    FCONST_1
    INVOKESTATIC net/minecraft/client/renderer/GlStateManager.color (FFFF)V
   L13
    LINENUMBER 104 L13
    INVOKESTATIC net/minecraft/client/renderer/GlStateManager.enableRescaleNormal ()V
   L14
    LINENUMBER 105 L14
    ALOAD 0
    ACONST_NULL
    PUTFIELD net/minecraft/client/gui/inventory/GuiContainer.theSlot : Lnet/minecraft/inventory/Slot;
   L15
    LINENUMBER 106 L15
    SIPUSH 240
    ISTORE 6
   L16
    LINENUMBER 107 L16
    SIPUSH 240
    ISTORE 7
   L17
    LINENUMBER 108 L17
    GETSTATIC net/minecraft/client/renderer/OpenGlHelper.lightmapTexUnit : I
    LDC 240.0
    LDC 240.0
    INVOKESTATIC net/minecraft/client/renderer/OpenGlHelper.setLightmapTextureCoords (IFF)V
   L18
    LINENUMBER 109 L18
    FCONST_1
    FCONST_1
    FCONST_1
    FCONST_1
    INVOKESTATIC net/minecraft/client/renderer/GlStateManager.color (FFFF)V
   L19
    LINENUMBER 111 L19
    ICONST_0
    ISTORE 8
   L20
   FRAME FULL [net/minecraft/client/gui/inventory/GuiContainer I I F I I I I I] []
    ILOAD 8
    ALOAD 0
    GETFIELD net/minecraft/client/gui/inventory/GuiContainer.inventorySlots : Lnet/minecraft/inventory/Container;
    GETFIELD net/minecraft/inventory/Container.inventorySlots : Ljava/util/List;
    INVOKEINTERFACE java/util/List.size ()I
    IF_ICMPGE L21
   L22
    LINENUMBER 113 L22
    ALOAD 0
    GETFIELD net/minecraft/client/gui/inventory/GuiContainer.inventorySlots : Lnet/minecraft/inventory/Container;
    GETFIELD net/minecraft/inventory/Container.inventorySlots : Ljava/util/List;
    ILOAD 8
    INVOKEINTERFACE java/util/List.get (I)Ljava/lang/Object;
    CHECKCAST net/minecraft/inventory/Slot
    ASTORE 9
   L23
    LINENUMBER 115 L23
    ALOAD 9
    INVOKEVIRTUAL net/minecraft/inventory/Slot.canBeHovered ()Z
    IFEQ L24
   L25
    LINENUMBER 117 L25
    ALOAD 0
    ALOAD 9
    INVOKESPECIAL net/minecraft/client/gui/inventory/GuiContainer.drawSlot (Lnet/minecraft/inventory/Slot;)V
   L24
    LINENUMBER 120 L24
   FRAME FULL [net/minecraft/client/gui/inventory/GuiContainer I I F I I I I I net/minecraft/inventory/Slot] []
    ALOAD 0
    ALOAD 9
    ILOAD 1
    ILOAD 2
    INVOKESPECIAL net/minecraft/client/gui/inventory/GuiContainer.isMouseOverSlot (Lnet/minecraft/inventory/Slot;II)Z
    IFEQ L26
    ALOAD 9
    INVOKEVIRTUAL net/minecraft/inventory/Slot.canBeHovered ()Z
    IFEQ L26
   L27
    LINENUMBER 122 L27
    ALOAD 0
    ALOAD 9
    PUTFIELD net/minecraft/client/gui/inventory/GuiContainer.theSlot : Lnet/minecraft/inventory/Slot;
   L28
    LINENUMBER 123 L28
    INVOKESTATIC net/minecraft/client/renderer/GlStateManager.disableLighting ()V
   L29
    LINENUMBER 124 L29
    INVOKESTATIC net/minecraft/client/renderer/GlStateManager.disableDepth ()V
   L30
    LINENUMBER 125 L30
    ALOAD 9
    GETFIELD net/minecraft/inventory/Slot.xPos : I
    ISTORE 10
   L31
    LINENUMBER 126 L31
    ALOAD 9
    GETFIELD net/minecraft/inventory/Slot.yPos : I
    ISTORE 11
   L32
    LINENUMBER 127 L32
    ICONST_1
    ICONST_1
    ICONST_1
    ICONST_0
    INVOKESTATIC net/minecraft/client/renderer/GlStateManager.colorMask (ZZZZ)V
   L33
    LINENUMBER 128 L33
    ALOAD 0
    ILOAD 10
    ILOAD 11
    ILOAD 10
    BIPUSH 16
    IADD
    ILOAD 11
    BIPUSH 16
    IADD
    LDC -2130706433
    LDC -2130706433
    INVOKEVIRTUAL net/minecraft/client/gui/inventory/GuiContainer.drawGradientRect (IIIIII)V
   L34
    LINENUMBER 129 L34
    ICONST_1
    ICONST_1
    ICONST_1
    ICONST_1
    INVOKESTATIC net/minecraft/client/renderer/GlStateManager.colorMask (ZZZZ)V
   L35
    LINENUMBER 130 L35
    INVOKESTATIC net/minecraft/client/renderer/GlStateManager.enableLighting ()V
   L36
    LINENUMBER 131 L36
    INVOKESTATIC net/minecraft/client/renderer/GlStateManager.enableDepth ()V
   L26
    LINENUMBER 111 L26
   FRAME FULL [net/minecraft/client/gui/inventory/GuiContainer I I F I I I I I net/minecraft/inventory/Slot] []
    IINC 8 1
    GOTO L20
   L21
    LINENUMBER 135 L21
   FRAME FULL [net/minecraft/client/gui/inventory/GuiContainer I I F I I I I I] []
    INVOKESTATIC net/minecraft/client/renderer/RenderHelper.disableStandardItemLighting ()V
   L37
    LINENUMBER 136 L37
    ALOAD 0
    ILOAD 1
    ILOAD 2
    INVOKEVIRTUAL net/minecraft/client/gui/inventory/GuiContainer.drawGuiContainerForegroundLayer (II)V
   L38
    LINENUMBER 137 L38
    INVOKESTATIC net/minecraft/client/renderer/RenderHelper.enableGUIStandardItemLighting ()V
    ALOAD 0
    INVOKESTATIC codechicken/lib/gui/GuiDraw.handleForegroundRender (Lnet/minecraft/client/gui/inventory/GuiContainer;)V
   L39
    LINENUMBER 138 L39
    ALOAD 0
    GETFIELD net/minecraft/client/gui/inventory/GuiContainer.mc : Lnet/minecraft/client/Minecraft;
    GETFIELD net/minecraft/client/Minecraft.player : Lnet/minecraft/client/entity/EntityPlayerSP;
    GETFIELD net/minecraft/client/entity/EntityPlayerSP.inventory : Lnet/minecraft/entity/player/InventoryPlayer;
    ASTORE 8
   L40
    LINENUMBER 139 L40
    ALOAD 0
    GETFIELD net/minecraft/client/gui/inventory/GuiContainer.draggedStack : Lnet/minecraft/item/ItemStack;
    INVOKEVIRTUAL net/minecraft/item/ItemStack.isEmpty ()Z
    IFEQ L41
    ALOAD 8
    INVOKEVIRTUAL net/minecraft/entity/player/InventoryPlayer.getItemStack ()Lnet/minecraft/item/ItemStack;
    GOTO L42
   L41
   FRAME FULL [net/minecraft/client/gui/inventory/GuiContainer I I F I I I I net/minecraft/entity/player/InventoryPlayer] []
    ALOAD 0
    GETFIELD net/minecraft/client/gui/inventory/GuiContainer.draggedStack : Lnet/minecraft/item/ItemStack;
   L42
   FRAME FULL [net/minecraft/client/gui/inventory/GuiContainer I I F I I I I net/minecraft/entity/player/InventoryPlayer] [net/minecraft/item/ItemStack]
    ASTORE 9
   L43
    LINENUMBER 141 L43
    ALOAD 9
    INVOKEVIRTUAL net/minecraft/item/ItemStack.isEmpty ()Z
    IFNE L44
   L45
    LINENUMBER 143 L45
    BIPUSH 8
    ISTORE 10
   L46
    LINENUMBER 144 L46
    ALOAD 0
    GETFIELD net/minecraft/client/gui/inventory/GuiContainer.draggedStack : Lnet/minecraft/item/ItemStack;
    INVOKEVIRTUAL net/minecraft/item/ItemStack.isEmpty ()Z
    IFEQ L47
    BIPUSH 8
    GOTO L48
   L47
   FRAME FULL [net/minecraft/client/gui/inventory/GuiContainer I I F I I I I net/minecraft/entity/player/InventoryPlayer net/minecraft/item/ItemStack I] []
    BIPUSH 16
   L48
   FRAME FULL [net/minecraft/client/gui/inventory/GuiContainer I I F I I I I net/minecraft/entity/player/InventoryPlayer net/minecraft/item/ItemStack I] [I]
    ISTORE 11
   L49
    LINENUMBER 145 L49
    ACONST_NULL
    ASTORE 12
   L50
    LINENUMBER 147 L50
    ALOAD 0
    GETFIELD net/minecraft/client/gui/inventory/GuiContainer.draggedStack : Lnet/minecraft/item/ItemStack;
    INVOKEVIRTUAL net/minecraft/item/ItemStack.isEmpty ()Z
    IFNE L51
    ALOAD 0
    GETFIELD net/minecraft/client/gui/inventory/GuiContainer.isRightMouseClick : Z
    IFEQ L51
   L52
    LINENUMBER 149 L52
    ALOAD 9
    INVOKEVIRTUAL net/minecraft/item/ItemStack.copy ()Lnet/minecraft/item/ItemStack;
    ASTORE 9
   L53
    LINENUMBER 150 L53
    ALOAD 9
    ALOAD 9
    INVOKEVIRTUAL net/minecraft/item/ItemStack.getCount ()I
    I2F
    FCONST_2
    FDIV
    INVOKESTATIC net/minecraft/util/math/MathHelper.ceil (F)I
    INVOKEVIRTUAL net/minecraft/item/ItemStack.setCount (I)V
    GOTO L54
   L51
    LINENUMBER 152 L51
   FRAME FULL [net/minecraft/client/gui/inventory/GuiContainer I I F I I I I net/minecraft/entity/player/InventoryPlayer net/minecraft/item/ItemStack I I N] []
    ALOAD 0
    GETFIELD net/minecraft/client/gui/inventory/GuiContainer.dragSplitting : Z
    IFEQ L54
    ALOAD 0
    GETFIELD net/minecraft/client/gui/inventory/GuiContainer.dragSplittingSlots : Ljava/util/Set;
    INVOKEINTERFACE java/util/Set.size ()I
    ICONST_1
    IF_ICMPLE L54
   L55
    LINENUMBER 154 L55
    ALOAD 9
    INVOKEVIRTUAL net/minecraft/item/ItemStack.copy ()Lnet/minecraft/item/ItemStack;
    ASTORE 9
   L56
    LINENUMBER 155 L56
    ALOAD 9
    ALOAD 0
    GETFIELD net/minecraft/client/gui/inventory/GuiContainer.dragSplittingRemnant : I
    INVOKEVIRTUAL net/minecraft/item/ItemStack.setCount (I)V
   L57
    LINENUMBER 157 L57
    ALOAD 9
    INVOKEVIRTUAL net/minecraft/item/ItemStack.isEmpty ()Z
    IFEQ L54
   L58
    LINENUMBER 159 L58
    NEW java/lang/StringBuilder
    DUP
    INVOKESPECIAL java/lang/StringBuilder.<init> ()V
    LDC ""
    INVOKEVIRTUAL java/lang/StringBuilder.append (Ljava/lang/String;)Ljava/lang/StringBuilder;
    GETSTATIC net/minecraft/util/text/TextFormatting.YELLOW : Lnet/minecraft/util/text/TextFormatting;
    INVOKEVIRTUAL java/lang/StringBuilder.append (Ljava/lang/Object;)Ljava/lang/StringBuilder;
    LDC "0"
    INVOKEVIRTUAL java/lang/StringBuilder.append (Ljava/lang/String;)Ljava/lang/StringBuilder;
    INVOKEVIRTUAL java/lang/StringBuilder.toString ()Ljava/lang/String;
    ASTORE 12
   L54
    LINENUMBER 163 L54
   FRAME FULL [net/minecraft/client/gui/inventory/GuiContainer I I F I I I I net/minecraft/entity/player/InventoryPlayer net/minecraft/item/ItemStack I I java/lang/String] []
    ALOAD 0
    ALOAD 9
    ILOAD 1
    ILOAD 4
    ISUB
    BIPUSH 8
    ISUB
    ILOAD 2
    ILOAD 5
    ISUB
    ILOAD 11
    ISUB
    ALOAD 12
    INVOKESPECIAL net/minecraft/client/gui/inventory/GuiContainer.drawItemStack (Lnet/minecraft/item/ItemStack;IILjava/lang/String;)V
   L44
    LINENUMBER 166 L44
   FRAME FULL [net/minecraft/client/gui/inventory/GuiContainer I I F I I I I net/minecraft/entity/player/InventoryPlayer net/minecraft/item/ItemStack] []
    ALOAD 0
    GETFIELD net/minecraft/client/gui/inventory/GuiContainer.returningStack : Lnet/minecraft/item/ItemStack;
    INVOKEVIRTUAL net/minecraft/item/ItemStack.isEmpty ()Z
    IFNE L59
   L60
    LINENUMBER 168 L60
    INVOKESTATIC net/minecraft/client/Minecraft.getSystemTime ()J
    ALOAD 0
    GETFIELD net/minecraft/client/gui/inventory/GuiContainer.returningStackTime : J
    LSUB
    L2F
    LDC 100.0
    FDIV
    FSTORE 10
   L61
    LINENUMBER 170 L61
    FLOAD 10
    FCONST_1
    FCMPL
    IFLT L62
   L63
    LINENUMBER 172 L63
    FCONST_1
    FSTORE 10
   L64
    LINENUMBER 173 L64
    ALOAD 0
    GETSTATIC net/minecraft/item/ItemStack.EMPTY : Lnet/minecraft/item/ItemStack;
    PUTFIELD net/minecraft/client/gui/inventory/GuiContainer.returningStack : Lnet/minecraft/item/ItemStack;
   L62
    LINENUMBER 176 L62
   FRAME FULL [net/minecraft/client/gui/inventory/GuiContainer I I F I I I I net/minecraft/entity/player/InventoryPlayer net/minecraft/item/ItemStack F] []
    ALOAD 0
    GETFIELD net/minecraft/client/gui/inventory/GuiContainer.returningStackDestSlot : Lnet/minecraft/inventory/Slot;
    GETFIELD net/minecraft/inventory/Slot.xPos : I
    ALOAD 0
    GETFIELD net/minecraft/client/gui/inventory/GuiContainer.touchUpX : I
    ISUB
    ISTORE 11
   L65
    LINENUMBER 177 L65
    ALOAD 0
    GETFIELD net/minecraft/client/gui/inventory/GuiContainer.returningStackDestSlot : Lnet/minecraft/inventory/Slot;
    GETFIELD net/minecraft/inventory/Slot.yPos : I
    ALOAD 0
    GETFIELD net/minecraft/client/gui/inventory/GuiContainer.touchUpY : I
    ISUB
    ISTORE 12
   L66
    LINENUMBER 178 L66
    ALOAD 0
    GETFIELD net/minecraft/client/gui/inventory/GuiContainer.touchUpX : I
    ILOAD 11
    I2F
    FLOAD 10
    FMUL
    F2I
    IADD
    ISTORE 13
   L67
    LINENUMBER 179 L67
    ALOAD 0
    GETFIELD net/minecraft/client/gui/inventory/GuiContainer.touchUpY : I
    ILOAD 12
    I2F
    FLOAD 10
    FMUL
    F2I
    IADD
    ISTORE 14
   L68
    LINENUMBER 180 L68
    ALOAD 0
    ALOAD 0
    GETFIELD net/minecraft/client/gui/inventory/GuiContainer.returningStack : Lnet/minecraft/item/ItemStack;
    ILOAD 13
    ILOAD 14
    ACONST_NULL
    CHECKCAST java/lang/String
    INVOKESPECIAL net/minecraft/client/gui/inventory/GuiContainer.drawItemStack (Lnet/minecraft/item/ItemStack;IILjava/lang/String;)V
   L59
    LINENUMBER 183 L59
   FRAME FULL [net/minecraft/client/gui/inventory/GuiContainer I I F I I I I net/minecraft/entity/player/InventoryPlayer net/minecraft/item/ItemStack] []
    INVOKESTATIC net/minecraft/client/renderer/GlStateManager.popMatrix ()V
   L69
    LINENUMBER 185 L69
    ALOAD 8
    INVOKEVIRTUAL net/minecraft/entity/player/InventoryPlayer.getItemStack ()Lnet/minecraft/item/ItemStack;
    INVOKEVIRTUAL net/minecraft/item/ItemStack.isEmpty ()Z
    IFEQ L70
    ALOAD 0
    GETFIELD net/minecraft/client/gui/inventory/GuiContainer.theSlot : Lnet/minecraft/inventory/Slot;
    IFNULL L70
    ALOAD 0
    GETFIELD net/minecraft/client/gui/inventory/GuiContainer.theSlot : Lnet/minecraft/inventory/Slot;
    INVOKEVIRTUAL net/minecraft/inventory/Slot.getHasStack ()Z
    IFEQ L70
   L71
    LINENUMBER 187 L71
    ALOAD 0
    GETFIELD net/minecraft/client/gui/inventory/GuiContainer.theSlot : Lnet/minecraft/inventory/Slot;
    INVOKEVIRTUAL net/minecraft/inventory/Slot.getStack ()Lnet/minecraft/item/ItemStack;
    ASTORE 10
   L72
    LINENUMBER 188 L72
    ALOAD 0
    ALOAD 10
    ILOAD 1
    ILOAD 2
    INVOKEVIRTUAL net/minecraft/client/gui/inventory/GuiContainer.renderToolTip (Lnet/minecraft/item/ItemStack;II)V
   L70
    LINENUMBER 191 L70
   FRAME FULL [net/minecraft/client/gui/inventory/GuiContainer I I F I I I I net/minecraft/entity/player/InventoryPlayer net/minecraft/item/ItemStack] []
    INVOKESTATIC net/minecraft/client/renderer/GlStateManager.enableLighting ()V
   L73
    LINENUMBER 192 L73
    INVOKESTATIC net/minecraft/client/renderer/GlStateManager.enableDepth ()V
   L74
    LINENUMBER 193 L74
    INVOKESTATIC net/minecraft/client/renderer/RenderHelper.enableStandardItemLighting ()V
   L75
    LINENUMBER 194 L75
    RETURN
   L76
    LOCALVARIABLE j1 I L31 L26 10
    LOCALVARIABLE k1 I L32 L26 11
    LOCALVARIABLE slot Lnet/minecraft/inventory/Slot; L23 L26 9
    LOCALVARIABLE i1 I L20 L21 8
    LOCALVARIABLE j2 I L46 L44 10
    LOCALVARIABLE k2 I L49 L44 11
    LOCALVARIABLE s Ljava/lang/String; L50 L44 12
    LOCALVARIABLE f F L61 L59 10
    LOCALVARIABLE l2 I L65 L59 11
    LOCALVARIABLE i3 I L66 L59 12
    LOCALVARIABLE l1 I L67 L59 13
    LOCALVARIABLE i2 I L68 L59 14
    LOCALVARIABLE itemstack1 Lnet/minecraft/item/ItemStack; L72 L70 10
    LOCALVARIABLE this Lnet/minecraft/client/gui/inventory/GuiContainer; L0 L76 0
    LOCALVARIABLE mouseX I L0 L76 1
    LOCALVARIABLE mouseY I L0 L76 2
    LOCALVARIABLE partialTicks F L0 L76 3
    LOCALVARIABLE i I L2 L76 4
    LOCALVARIABLE j I L3 L76 5
    LOCALVARIABLE k I L16 L76 6
    LOCALVARIABLE l I L17 L76 7
    LOCALVARIABLE inventoryplayer Lnet/minecraft/entity/player/InventoryPlayer; L40 L76 8
    LOCALVARIABLE itemstack Lnet/minecraft/item/ItemStack; L43 L76 9
    MAXSTACK = 7
    MAXLOCALS = 15

  // access flags 0x2
  private drawItemStack(Lnet/minecraft/item/ItemStack;IILjava/lang/String;)V
   L0
    LINENUMBER 203 L0
    FCONST_0
    FCONST_0
    LDC 32.0
    INVOKESTATIC net/minecraft/client/renderer/GlStateManager.translate (FFF)V
   L1
    LINENUMBER 204 L1
    ALOAD 0
    LDC 200.0
    PUTFIELD net/minecraft/client/gui/inventory/GuiContainer.zLevel : F
   L2
    LINENUMBER 205 L2
    ALOAD 0
    GETFIELD net/minecraft/client/gui/inventory/GuiContainer.itemRender : Lnet/minecraft/client/renderer/RenderItem;
    LDC 200.0
    PUTFIELD net/minecraft/client/renderer/RenderItem.zLevel : F
   L3
    LINENUMBER 206 L3
    ALOAD 1
    INVOKEVIRTUAL net/minecraft/item/ItemStack.getItem ()Lnet/minecraft/item/Item;
    ALOAD 1
    INVOKEVIRTUAL net/minecraft/item/Item.getFontRenderer (Lnet/minecraft/item/ItemStack;)Lnet/minecraft/client/gui/FontRenderer;
    ASTORE 5
   L4
    LINENUMBER 207 L4
    ALOAD 5
    IFNONNULL L5
    ALOAD 0
    GETFIELD net/minecraft/client/gui/inventory/GuiContainer.fontRenderer : Lnet/minecraft/client/gui/FontRenderer;
    ASTORE 5
   L5
    LINENUMBER 208 L5
   FRAME FULL [net/minecraft/client/gui/inventory/GuiContainer net/minecraft/item/ItemStack I I java/lang/String net/minecraft/client/gui/FontRenderer] []
    ALOAD 0
    GETFIELD net/minecraft/client/gui/inventory/GuiContainer.itemRender : Lnet/minecraft/client/renderer/RenderItem;
    ALOAD 1
    ILOAD 2
    ILOAD 3
    INVOKEVIRTUAL net/minecraft/client/renderer/RenderItem.renderItemAndEffectIntoGUI (Lnet/minecraft/item/ItemStack;II)V
   L6
    LINENUMBER 209 L6
    ALOAD 0
    GETFIELD net/minecraft/client/gui/inventory/GuiContainer.itemRender : Lnet/minecraft/client/renderer/RenderItem;
    ALOAD 5
    ALOAD 1
    ILOAD 2
    ILOAD 3
    ALOAD 0
    GETFIELD net/minecraft/client/gui/inventory/GuiContainer.draggedStack : Lnet/minecraft/item/ItemStack;
    INVOKEVIRTUAL net/minecraft/item/ItemStack.isEmpty ()Z
    IFEQ L7
    ICONST_0
    GOTO L8
   L7
   FRAME FULL [net/minecraft/client/gui/inventory/GuiContainer net/minecraft/item/ItemStack I I java/lang/String net/minecraft/client/gui/FontRenderer] [net/minecraft/client/renderer/RenderItem net/minecraft/client/gui/FontRenderer net/minecraft/item/ItemStack I I]
    BIPUSH 8
   L8
   FRAME FULL [net/minecraft/client/gui/inventory/GuiContainer net/minecraft/item/ItemStack I I java/lang/String net/minecraft/client/gui/FontRenderer] [net/minecraft/client/renderer/RenderItem net/minecraft/client/gui/FontRenderer net/minecraft/item/ItemStack I I I]
    ISUB
    ALOAD 4
    INVOKEVIRTUAL net/minecraft/client/renderer/RenderItem.renderItemOverlayIntoGUI (Lnet/minecraft/client/gui/FontRenderer;Lnet/minecraft/item/ItemStack;IILjava/lang/String;)V
   L9
    LINENUMBER 210 L9
    ALOAD 0
    FCONST_0
    PUTFIELD net/minecraft/client/gui/inventory/GuiContainer.zLevel : F
   L10
    LINENUMBER 211 L10
    ALOAD 0
    GETFIELD net/minecraft/client/gui/inventory/GuiContainer.itemRender : Lnet/minecraft/client/renderer/RenderItem;
    FCONST_0
    PUTFIELD net/minecraft/client/renderer/RenderItem.zLevel : F
   L11
    LINENUMBER 212 L11
    RETURN
   L12
    LOCALVARIABLE this Lnet/minecraft/client/gui/inventory/GuiContainer; L0 L12 0
    LOCALVARIABLE stack Lnet/minecraft/item/ItemStack; L0 L12 1
    LOCALVARIABLE x I L0 L12 2
    LOCALVARIABLE y I L0 L12 3
    LOCALVARIABLE altText Ljava/lang/String; L0 L12 4
    LOCALVARIABLE font Lnet/minecraft/client/gui/FontRenderer; L4 L12 5
    MAXSTACK = 6
    MAXLOCALS = 6

  // access flags 0x4
  protected drawGuiContainerForegroundLayer(II)V
   L0
    LINENUMBER 219 L0
    RETURN
   L1
    LOCALVARIABLE this Lnet/minecraft/client/gui/inventory/GuiContainer; L0 L1 0
    LOCALVARIABLE mouseX I L0 L1 1
    LOCALVARIABLE mouseY I L0 L1 2
    MAXSTACK = 0
    MAXLOCALS = 3

  // access flags 0x404
  protected abstract drawGuiContainerBackgroundLayer(FII)V

  // access flags 0x2
  private drawSlot(Lnet/minecraft/inventory/Slot;)V
   L0
    LINENUMBER 231 L0
    ALOAD 1
    GETFIELD net/minecraft/inventory/Slot.xPos : I
    ISTORE 2
   L1
    LINENUMBER 232 L1
    ALOAD 1
    GETFIELD net/minecraft/inventory/Slot.yPos : I
    ISTORE 3
   L2
    LINENUMBER 233 L2
    ALOAD 1
    INVOKEVIRTUAL net/minecraft/inventory/Slot.getStack ()Lnet/minecraft/item/ItemStack;
    ASTORE 4
   L3
    LINENUMBER 234 L3
    ICONST_0
    ISTORE 5
   L4
    LINENUMBER 235 L4
    ALOAD 1
    ALOAD 0
    GETFIELD net/minecraft/client/gui/inventory/GuiContainer.clickedSlot : Lnet/minecraft/inventory/Slot;
    IF_ACMPNE L5
    ALOAD 0
    GETFIELD net/minecraft/client/gui/inventory/GuiContainer.draggedStack : Lnet/minecraft/item/ItemStack;
    INVOKEVIRTUAL net/minecraft/item/ItemStack.isEmpty ()Z
    IFNE L5
    ALOAD 0
    GETFIELD net/minecraft/client/gui/inventory/GuiContainer.isRightMouseClick : Z
    IFNE L5
    ICONST_1
    GOTO L6
   L5
   FRAME FULL [net/minecraft/client/gui/inventory/GuiContainer net/minecraft/inventory/Slot I I net/minecraft/item/ItemStack I] []
    ICONST_0
   L6
   FRAME FULL [net/minecraft/client/gui/inventory/GuiContainer net/minecraft/inventory/Slot I I net/minecraft/item/ItemStack I] [I]
    ISTORE 6
   L7
    LINENUMBER 236 L7
    ALOAD 0
    GETFIELD net/minecraft/client/gui/inventory/GuiContainer.mc : Lnet/minecraft/client/Minecraft;
    GETFIELD net/minecraft/client/Minecraft.player : Lnet/minecraft/client/entity/EntityPlayerSP;
    GETFIELD net/minecraft/client/entity/EntityPlayerSP.inventory : Lnet/minecraft/entity/player/InventoryPlayer;
    INVOKEVIRTUAL net/minecraft/entity/player/InventoryPlayer.getItemStack ()Lnet/minecraft/item/ItemStack;
    ASTORE 7
   L8
    LINENUMBER 237 L8
    ACONST_NULL
    ASTORE 8
   L9
    LINENUMBER 239 L9
    ALOAD 1
    ALOAD 0
    GETFIELD net/minecraft/client/gui/inventory/GuiContainer.clickedSlot : Lnet/minecraft/inventory/Slot;
    IF_ACMPNE L10
    ALOAD 0
    GETFIELD net/minecraft/client/gui/inventory/GuiContainer.draggedStack : Lnet/minecraft/item/ItemStack;
    INVOKEVIRTUAL net/minecraft/item/ItemStack.isEmpty ()Z
    IFNE L10
    ALOAD 0
    GETFIELD net/minecraft/client/gui/inventory/GuiContainer.isRightMouseClick : Z
    IFEQ L10
    ALOAD 4
    INVOKEVIRTUAL net/minecraft/item/ItemStack.isEmpty ()Z
    IFNE L10
   L11
    LINENUMBER 241 L11
    ALOAD 4
    INVOKEVIRTUAL net/minecraft/item/ItemStack.copy ()Lnet/minecraft/item/ItemStack;
    ASTORE 4
   L12
    LINENUMBER 242 L12
    ALOAD 4
    ALOAD 4
    INVOKEVIRTUAL net/minecraft/item/ItemStack.getCount ()I
    ICONST_2
    IDIV
    INVOKEVIRTUAL net/minecraft/item/ItemStack.setCount (I)V
    GOTO L13
   L10
    LINENUMBER 244 L10
   FRAME FULL [net/minecraft/client/gui/inventory/GuiContainer net/minecraft/inventory/Slot I I net/minecraft/item/ItemStack I I net/minecraft/item/ItemStack N] []
    ALOAD 0
    GETFIELD net/minecraft/client/gui/inventory/GuiContainer.dragSplitting : Z
    IFEQ L13
    ALOAD 0
    GETFIELD net/minecraft/client/gui/inventory/GuiContainer.dragSplittingSlots : Ljava/util/Set;
    ALOAD 1
    INVOKEINTERFACE java/util/Set.contains (Ljava/lang/Object;)Z
    IFEQ L13
    ALOAD 7
    INVOKEVIRTUAL net/minecraft/item/ItemStack.isEmpty ()Z
    IFNE L13
   L14
    LINENUMBER 246 L14
    ALOAD 0
    GETFIELD net/minecraft/client/gui/inventory/GuiContainer.dragSplittingSlots : Ljava/util/Set;
    INVOKEINTERFACE java/util/Set.size ()I
    ICONST_1
    IF_ICMPNE L15
   L16
    LINENUMBER 248 L16
    RETURN
   L15
    LINENUMBER 251 L15
   FRAME FULL [net/minecraft/client/gui/inventory/GuiContainer net/minecraft/inventory/Slot I I net/minecraft/item/ItemStack I I net/minecraft/item/ItemStack N] []
    ALOAD 1
    ALOAD 7
    ICONST_1
    INVOKESTATIC net/minecraft/inventory/Container.canAddItemToSlot (Lnet/minecraft/inventory/Slot;Lnet/minecraft/item/ItemStack;Z)Z
    IFEQ L17
    ALOAD 0
    GETFIELD net/minecraft/client/gui/inventory/GuiContainer.inventorySlots : Lnet/minecraft/inventory/Container;
    ALOAD 1
    INVOKEVIRTUAL net/minecraft/inventory/Container.canDragIntoSlot (Lnet/minecraft/inventory/Slot;)Z
    IFEQ L17
   L18
    LINENUMBER 253 L18
    ALOAD 7
    INVOKEVIRTUAL net/minecraft/item/ItemStack.copy ()Lnet/minecraft/item/ItemStack;
    ASTORE 4
   L19
    LINENUMBER 254 L19
    ICONST_1
    ISTORE 5
   L20
    LINENUMBER 255 L20
    ALOAD 0
    GETFIELD net/minecraft/client/gui/inventory/GuiContainer.dragSplittingSlots : Ljava/util/Set;
    ALOAD 0
    GETFIELD net/minecraft/client/gui/inventory/GuiContainer.dragSplittingLimit : I
    ALOAD 4
    ALOAD 1
    INVOKEVIRTUAL net/minecraft/inventory/Slot.getStack ()Lnet/minecraft/item/ItemStack;
    INVOKEVIRTUAL net/minecraft/item/ItemStack.isEmpty ()Z
    IFEQ L21
    ICONST_0
    GOTO L22
   L21
   FRAME FULL [net/minecraft/client/gui/inventory/GuiContainer net/minecraft/inventory/Slot I I net/minecraft/item/ItemStack I I net/minecraft/item/ItemStack N] [java/util/Set I net/minecraft/item/ItemStack]
    ALOAD 1
    INVOKEVIRTUAL net/minecraft/inventory/Slot.getStack ()Lnet/minecraft/item/ItemStack;
    INVOKEVIRTUAL net/minecraft/item/ItemStack.getCount ()I
   L22
   FRAME FULL [net/minecraft/client/gui/inventory/GuiContainer net/minecraft/inventory/Slot I I net/minecraft/item/ItemStack I I net/minecraft/item/ItemStack N] [java/util/Set I net/minecraft/item/ItemStack I]
    INVOKESTATIC net/minecraft/inventory/Container.computeStackSize (Ljava/util/Set;ILnet/minecraft/item/ItemStack;I)V
   L23
    LINENUMBER 256 L23
    ALOAD 4
    INVOKEVIRTUAL net/minecraft/item/ItemStack.getMaxStackSize ()I
    ALOAD 1
    ALOAD 4
    INVOKEVIRTUAL net/minecraft/inventory/Slot.getItemStackLimit (Lnet/minecraft/item/ItemStack;)I
    INVOKESTATIC java/lang/Math.min (II)I
    ISTORE 9
   L24
    LINENUMBER 258 L24
    ALOAD 4
    INVOKEVIRTUAL net/minecraft/item/ItemStack.getCount ()I
    ILOAD 9
    IF_ICMPLE L25
   L26
    LINENUMBER 260 L26
    NEW java/lang/StringBuilder
    DUP
    INVOKESPECIAL java/lang/StringBuilder.<init> ()V
    GETSTATIC net/minecraft/util/text/TextFormatting.YELLOW : Lnet/minecraft/util/text/TextFormatting;
    INVOKEVIRTUAL net/minecraft/util/text/TextFormatting.toString ()Ljava/lang/String;
    INVOKEVIRTUAL java/lang/StringBuilder.append (Ljava/lang/String;)Ljava/lang/StringBuilder;
    ILOAD 9
    INVOKEVIRTUAL java/lang/StringBuilder.append (I)Ljava/lang/StringBuilder;
    INVOKEVIRTUAL java/lang/StringBuilder.toString ()Ljava/lang/String;
    ASTORE 8
   L27
    LINENUMBER 261 L27
    ALOAD 4
    ILOAD 9
    INVOKEVIRTUAL net/minecraft/item/ItemStack.setCount (I)V
   L25
    LINENUMBER 263 L25
   FRAME FULL [net/minecraft/client/gui/inventory/GuiContainer net/minecraft/inventory/Slot I I net/minecraft/item/ItemStack I I net/minecraft/item/ItemStack java/lang/String I] []
    GOTO L13
   L17
    LINENUMBER 266 L17
   FRAME FULL [net/minecraft/client/gui/inventory/GuiContainer net/minecraft/inventory/Slot I I net/minecraft/item/ItemStack I I net/minecraft/item/ItemStack N] []
    ALOAD 0
    GETFIELD net/minecraft/client/gui/inventory/GuiContainer.dragSplittingSlots : Ljava/util/Set;
    ALOAD 1
    INVOKEINTERFACE java/util/Set.remove (Ljava/lang/Object;)Z
    POP
   L28
    LINENUMBER 267 L28
    ALOAD 0
    INVOKESPECIAL net/minecraft/client/gui/inventory/GuiContainer.updateDragSplitting ()V
   L13
    LINENUMBER 271 L13
   FRAME FULL [net/minecraft/client/gui/inventory/GuiContainer net/minecraft/inventory/Slot I I net/minecraft/item/ItemStack I I net/minecraft/item/ItemStack java/lang/String] []
    ALOAD 0
    LDC 100.0
    PUTFIELD net/minecraft/client/gui/inventory/GuiContainer.zLevel : F
   L29
    LINENUMBER 272 L29
    ALOAD 0
    GETFIELD net/minecraft/client/gui/inventory/GuiContainer.itemRender : Lnet/minecraft/client/renderer/RenderItem;
    LDC 100.0
    PUTFIELD net/minecraft/client/renderer/RenderItem.zLevel : F
   L30
    LINENUMBER 274 L30
    ALOAD 4
    INVOKEVIRTUAL net/minecraft/item/ItemStack.isEmpty ()Z
    IFEQ L31
    ALOAD 1
    INVOKEVIRTUAL net/minecraft/inventory/Slot.canBeHovered ()Z
    IFEQ L31
   L32
    LINENUMBER 276 L32
    ALOAD 1
    INVOKEVIRTUAL net/minecraft/inventory/Slot.getBackgroundSprite ()Lnet/minecraft/client/renderer/texture/TextureAtlasSprite;
    ASTORE 9
   L33
    LINENUMBER 278 L33
    ALOAD 9
    IFNULL L31
   L34
    LINENUMBER 280 L34
    INVOKESTATIC net/minecraft/client/renderer/GlStateManager.disableLighting ()V
   L35
    LINENUMBER 281 L35
    ALOAD 0
    GETFIELD net/minecraft/client/gui/inventory/GuiContainer.mc : Lnet/minecraft/client/Minecraft;
    INVOKEVIRTUAL net/minecraft/client/Minecraft.getTextureManager ()Lnet/minecraft/client/renderer/texture/TextureManager;
    ALOAD 1
    INVOKEVIRTUAL net/minecraft/inventory/Slot.getBackgroundLocation ()Lnet/minecraft/util/ResourceLocation;
    INVOKEVIRTUAL net/minecraft/client/renderer/texture/TextureManager.bindTexture (Lnet/minecraft/util/ResourceLocation;)V
   L36
    LINENUMBER 282 L36
    ALOAD 0
    ILOAD 2
    ILOAD 3
    ALOAD 9
    BIPUSH 16
    BIPUSH 16
    INVOKEVIRTUAL net/minecraft/client/gui/inventory/GuiContainer.drawTexturedModalRect (IILnet/minecraft/client/renderer/texture/TextureAtlasSprite;II)V
   L37
    LINENUMBER 283 L37
    INVOKESTATIC net/minecraft/client/renderer/GlStateManager.enableLighting ()V
   L38
    LINENUMBER 284 L38
    ICONST_1
    ISTORE 6
   L31
    LINENUMBER 288 L31
   FRAME FULL [net/minecraft/client/gui/inventory/GuiContainer net/minecraft/inventory/Slot I I net/minecraft/item/ItemStack I I net/minecraft/item/ItemStack java/lang/String] []
    ILOAD 6
    IFNE L39
   L40
    LINENUMBER 290 L40
    ILOAD 5
    IFEQ L41
   L42
    LINENUMBER 292 L42
    ILOAD 2
    ILOAD 3
    ILOAD 2
    BIPUSH 16
    IADD
    ILOAD 3
    BIPUSH 16
    IADD
    LDC -2130706433
    INVOKESTATIC net/minecraft/client/gui/inventory/GuiContainer.drawRect (IIIII)V
   L41
    LINENUMBER 295 L41
   FRAME FULL [net/minecraft/client/gui/inventory/GuiContainer net/minecraft/inventory/Slot I I net/minecraft/item/ItemStack I I net/minecraft/item/ItemStack java/lang/String] []
    INVOKESTATIC net/minecraft/client/renderer/GlStateManager.enableDepth ()V
   L43
    LINENUMBER 296 L43
    ALOAD 0
    GETFIELD net/minecraft/client/gui/inventory/GuiContainer.itemRender : Lnet/minecraft/client/renderer/RenderItem;
    ALOAD 0
    GETFIELD net/minecraft/client/gui/inventory/GuiContainer.mc : Lnet/minecraft/client/Minecraft;
    GETFIELD net/minecraft/client/Minecraft.player : Lnet/minecraft/client/entity/EntityPlayerSP;
    ALOAD 4
    ILOAD 2
    ILOAD 3
    INVOKEVIRTUAL net/minecraft/client/renderer/RenderItem.renderItemAndEffectIntoGUI (Lnet/minecraft/entity/EntityLivingBase;Lnet/minecraft/item/ItemStack;II)V
   L44
    LINENUMBER 297 L44
    ALOAD 0
    GETFIELD net/minecraft/client/gui/inventory/GuiContainer.itemRender : Lnet/minecraft/client/renderer/RenderItem;
    ALOAD 0
    GETFIELD net/minecraft/client/gui/inventory/GuiContainer.fontRenderer : Lnet/minecraft/client/gui/FontRenderer;
    ALOAD 4
    ILOAD 2
    ILOAD 3
    ALOAD 8
    INVOKEVIRTUAL net/minecraft/client/renderer/RenderItem.renderItemOverlayIntoGUI (Lnet/minecraft/client/gui/FontRenderer;Lnet/minecraft/item/ItemStack;IILjava/lang/String;)V
   L39
    LINENUMBER 300 L39
   FRAME FULL [net/minecraft/client/gui/inventory/GuiContainer net/minecraft/inventory/Slot I I net/minecraft/item/ItemStack I I net/minecraft/item/ItemStack java/lang/String] []
    ALOAD 0
    GETFIELD net/minecraft/client/gui/inventory/GuiContainer.itemRender : Lnet/minecraft/client/renderer/RenderItem;
    FCONST_0
    PUTFIELD net/minecraft/client/renderer/RenderItem.zLevel : F
   L45
    LINENUMBER 301 L45
    ALOAD 0
    FCONST_0
    PUTFIELD net/minecraft/client/gui/inventory/GuiContainer.zLevel : F
   L46
    LINENUMBER 302 L46
    RETURN
   L47
    LOCALVARIABLE k I L24 L25 9
    LOCALVARIABLE textureatlassprite Lnet/minecraft/client/renderer/texture/TextureAtlasSprite; L33 L31 9
    LOCALVARIABLE this Lnet/minecraft/client/gui/inventory/GuiContainer; L0 L47 0
    LOCALVARIABLE slotIn Lnet/minecraft/inventory/Slot; L0 L47 1
    LOCALVARIABLE i I L1 L47 2
    LOCALVARIABLE j I L2 L47 3
    LOCALVARIABLE itemstack Lnet/minecraft/item/ItemStack; L3 L47 4
    LOCALVARIABLE flag Z L4 L47 5
    LOCALVARIABLE flag1 Z L7 L47 6
    LOCALVARIABLE itemstack1 Lnet/minecraft/item/ItemStack; L8 L47 7
    LOCALVARIABLE s Ljava/lang/String; L9 L47 8
    MAXSTACK = 6
    MAXLOCALS = 10

  // access flags 0x2
  private updateDragSplitting()V
   L0
    LINENUMBER 306 L0
    ALOAD 0
    GETFIELD net/minecraft/client/gui/inventory/GuiContainer.mc : Lnet/minecraft/client/Minecraft;
    GETFIELD net/minecraft/client/Minecraft.player : Lnet/minecraft/client/entity/EntityPlayerSP;
    GETFIELD net/minecraft/client/entity/EntityPlayerSP.inventory : Lnet/minecraft/entity/player/InventoryPlayer;
    INVOKEVIRTUAL net/minecraft/entity/player/InventoryPlayer.getItemStack ()Lnet/minecraft/item/ItemStack;
    ASTORE 1
   L1
    LINENUMBER 308 L1
    ALOAD 1
    INVOKEVIRTUAL net/minecraft/item/ItemStack.isEmpty ()Z
    IFNE L2
    ALOAD 0
    GETFIELD net/minecraft/client/gui/inventory/GuiContainer.dragSplitting : Z
    IFEQ L2
   L3
    LINENUMBER 310 L3
    ALOAD 0
    GETFIELD net/minecraft/client/gui/inventory/GuiContainer.dragSplittingLimit : I
    ICONST_2
    IF_ICMPNE L4
   L5
    LINENUMBER 312 L5
    ALOAD 0
    ALOAD 1
    INVOKEVIRTUAL net/minecraft/item/ItemStack.getMaxStackSize ()I
    PUTFIELD net/minecraft/client/gui/inventory/GuiContainer.dragSplittingRemnant : I
    GOTO L2
   L4
    LINENUMBER 316 L4
   FRAME FULL [net/minecraft/client/gui/inventory/GuiContainer net/minecraft/item/ItemStack] []
    ALOAD 0
    ALOAD 1
    INVOKEVIRTUAL net/minecraft/item/ItemStack.getCount ()I
    PUTFIELD net/minecraft/client/gui/inventory/GuiContainer.dragSplittingRemnant : I
   L6
    LINENUMBER 318 L6
    ALOAD 0
    GETFIELD net/minecraft/client/gui/inventory/GuiContainer.dragSplittingSlots : Ljava/util/Set;
    INVOKEINTERFACE java/util/Set.iterator ()Ljava/util/Iterator;
    ASTORE 2
   L7
   FRAME FULL [net/minecraft/client/gui/inventory/GuiContainer net/minecraft/item/ItemStack java/util/Iterator] []
    ALOAD 2
    INVOKEINTERFACE java/util/Iterator.hasNext ()Z
    IFEQ L2
    ALOAD 2
    INVOKEINTERFACE java/util/Iterator.next ()Ljava/lang/Object;
    CHECKCAST net/minecraft/inventory/Slot
    ASTORE 3
   L8
    LINENUMBER 320 L8
    ALOAD 1
    INVOKEVIRTUAL net/minecraft/item/ItemStack.copy ()Lnet/minecraft/item/ItemStack;
    ASTORE 4
   L9
    LINENUMBER 321 L9
    ALOAD 3
    INVOKEVIRTUAL net/minecraft/inventory/Slot.getStack ()Lnet/minecraft/item/ItemStack;
    ASTORE 5
   L10
    LINENUMBER 322 L10
    ALOAD 5
    INVOKEVIRTUAL net/minecraft/item/ItemStack.isEmpty ()Z
    IFEQ L11
    ICONST_0
    GOTO L12
   L11
   FRAME FULL [net/minecraft/client/gui/inventory/GuiContainer net/minecraft/item/ItemStack java/util/Iterator net/minecraft/inventory/Slot net/minecraft/item/ItemStack net/minecraft/item/ItemStack] []
    ALOAD 5
    INVOKEVIRTUAL net/minecraft/item/ItemStack.getCount ()I
   L12
   FRAME FULL [net/minecraft/client/gui/inventory/GuiContainer net/minecraft/item/ItemStack java/util/Iterator net/minecraft/inventory/Slot net/minecraft/item/ItemStack net/minecraft/item/ItemStack] [I]
    ISTORE 6
   L13
    LINENUMBER 323 L13
    ALOAD 0
    GETFIELD net/minecraft/client/gui/inventory/GuiContainer.dragSplittingSlots : Ljava/util/Set;
    ALOAD 0
    GETFIELD net/minecraft/client/gui/inventory/GuiContainer.dragSplittingLimit : I
    ALOAD 4
    ILOAD 6
    INVOKESTATIC net/minecraft/inventory/Container.computeStackSize (Ljava/util/Set;ILnet/minecraft/item/ItemStack;I)V
   L14
    LINENUMBER 324 L14
    ALOAD 4
    INVOKEVIRTUAL net/minecraft/item/ItemStack.getMaxStackSize ()I
    ALOAD 3
    ALOAD 4
    INVOKEVIRTUAL net/minecraft/inventory/Slot.getItemStackLimit (Lnet/minecraft/item/ItemStack;)I
    INVOKESTATIC java/lang/Math.min (II)I
    ISTORE 7
   L15
    LINENUMBER 326 L15
    ALOAD 4
    INVOKEVIRTUAL net/minecraft/item/ItemStack.getCount ()I
    ILOAD 7
    IF_ICMPLE L16
   L17
    LINENUMBER 328 L17
    ALOAD 4
    ILOAD 7
    INVOKEVIRTUAL net/minecraft/item/ItemStack.setCount (I)V
   L16
    LINENUMBER 331 L16
   FRAME FULL [net/minecraft/client/gui/inventory/GuiContainer net/minecraft/item/ItemStack java/util/Iterator net/minecraft/inventory/Slot net/minecraft/item/ItemStack net/minecraft/item/ItemStack I I] []
    ALOAD 0
    DUP
    GETFIELD net/minecraft/client/gui/inventory/GuiContainer.dragSplittingRemnant : I
    ALOAD 4
    INVOKEVIRTUAL net/minecraft/item/ItemStack.getCount ()I
    ILOAD 6
    ISUB
    ISUB
    PUTFIELD net/minecraft/client/gui/inventory/GuiContainer.dragSplittingRemnant : I
   L18
    LINENUMBER 332 L18
    GOTO L7
   L2
    LINENUMBER 335 L2
   FRAME FULL [net/minecraft/client/gui/inventory/GuiContainer net/minecraft/item/ItemStack] []
    RETURN
   L19
    LOCALVARIABLE itemstack1 Lnet/minecraft/item/ItemStack; L9 L18 4
    LOCALVARIABLE itemstack2 Lnet/minecraft/item/ItemStack; L10 L18 5
    LOCALVARIABLE i I L13 L18 6
    LOCALVARIABLE j I L15 L18 7
    LOCALVARIABLE slot Lnet/minecraft/inventory/Slot; L8 L18 3
    LOCALVARIABLE this Lnet/minecraft/client/gui/inventory/GuiContainer; L0 L19 0
    LOCALVARIABLE itemstack Lnet/minecraft/item/ItemStack; L1 L19 1
    MAXSTACK = 4
    MAXLOCALS = 8

  // access flags 0x2
  private getSlotAtPosition(II)Lnet/minecraft/inventory/Slot;
   L0
    LINENUMBER 342 L0
    ICONST_0
    ISTORE 3
   L1
   FRAME FULL [net/minecraft/client/gui/inventory/GuiContainer I I I] []
    ILOAD 3
    ALOAD 0
    GETFIELD net/minecraft/client/gui/inventory/GuiContainer.inventorySlots : Lnet/minecraft/inventory/Container;
    GETFIELD net/minecraft/inventory/Container.inventorySlots : Ljava/util/List;
    INVOKEINTERFACE java/util/List.size ()I
    IF_ICMPGE L2
   L3
    LINENUMBER 344 L3
    ALOAD 0
    GETFIELD net/minecraft/client/gui/inventory/GuiContainer.inventorySlots : Lnet/minecraft/inventory/Container;
    GETFIELD net/minecraft/inventory/Container.inventorySlots : Ljava/util/List;
    ILOAD 3
    INVOKEINTERFACE java/util/List.get (I)Ljava/lang/Object;
    CHECKCAST net/minecraft/inventory/Slot
    ASTORE 4
   L4
    LINENUMBER 346 L4
    ALOAD 0
    ALOAD 4
    ILOAD 1
    ILOAD 2
    INVOKESPECIAL net/minecraft/client/gui/inventory/GuiContainer.isMouseOverSlot (Lnet/minecraft/inventory/Slot;II)Z
    IFEQ L5
    ALOAD 4
    INVOKEVIRTUAL net/minecraft/inventory/Slot.canBeHovered ()Z
    IFEQ L5
   L6
    LINENUMBER 348 L6
    ALOAD 4
    ARETURN
   L5
    LINENUMBER 342 L5
   FRAME FULL [net/minecraft/client/gui/inventory/GuiContainer I I I net/minecraft/inventory/Slot] []
    IINC 3 1
    GOTO L1
   L2
    LINENUMBER 352 L2
   FRAME FULL [net/minecraft/client/gui/inventory/GuiContainer I I I] []
    ACONST_NULL
    ARETURN
   L7
    LOCALVARIABLE slot Lnet/minecraft/inventory/Slot; L4 L5 4
    LOCALVARIABLE i I L1 L2 3
    LOCALVARIABLE this Lnet/minecraft/client/gui/inventory/GuiContainer; L0 L7 0
    LOCALVARIABLE x I L0 L7 1
    LOCALVARIABLE y I L0 L7 2
    MAXSTACK = 4
    MAXLOCALS = 5

  // access flags 0x4
  protected mouseClicked(III)V throws java/io/IOException 
   L0
    LINENUMBER 360 L0
    ALOAD 0
    ILOAD 1
    ILOAD 2
    ILOAD 3
    INVOKESPECIAL net/minecraft/client/gui/GuiScreen.mouseClicked (III)V
   L1
    LINENUMBER 361 L1
    ALOAD 0
    GETFIELD net/minecraft/client/gui/inventory/GuiContainer.mc : Lnet/minecraft/client/Minecraft;
    GETFIELD net/minecraft/client/Minecraft.gameSettings : Lnet/minecraft/client/settings/GameSettings;
    GETFIELD net/minecraft/client/settings/GameSettings.keyBindPickBlock : Lnet/minecraft/client/settings/KeyBinding;
    ILOAD 3
    BIPUSH 100
    ISUB
    INVOKEVIRTUAL net/minecraft/client/settings/KeyBinding.isActiveAndMatches (I)Z
    ISTORE 4
   L2
    LINENUMBER 362 L2
    ALOAD 0
    ILOAD 1
    ILOAD 2
    INVOKESPECIAL net/minecraft/client/gui/inventory/GuiContainer.getSlotAtPosition (II)Lnet/minecraft/inventory/Slot;
    ASTORE 5
   L3
    LINENUMBER 363 L3
    INVOKESTATIC net/minecraft/client/Minecraft.getSystemTime ()J
    LSTORE 6
   L4
    LINENUMBER 364 L4
    ALOAD 0
    ALOAD 0
    GETFIELD net/minecraft/client/gui/inventory/GuiContainer.lastClickSlot : Lnet/minecraft/inventory/Slot;
    ALOAD 5
    IF_ACMPNE L5
    LLOAD 6
    ALOAD 0
    GETFIELD net/minecraft/client/gui/inventory/GuiContainer.lastClickTime : J
    LSUB
    LDC 250
    LCMP
    IFGE L5
    ALOAD 0
    GETFIELD net/minecraft/client/gui/inventory/GuiContainer.lastClickButton : I
    ILOAD 3
    IF_ICMPNE L5
    ICONST_1
    GOTO L6
   L5
   FRAME FULL [net/minecraft/client/gui/inventory/GuiContainer I I I I net/minecraft/inventory/Slot J] [net/minecraft/client/gui/inventory/GuiContainer]
    ICONST_0
   L6
   FRAME FULL [net/minecraft/client/gui/inventory/GuiContainer I I I I net/minecraft/inventory/Slot J] [net/minecraft/client/gui/inventory/GuiContainer I]
    PUTFIELD net/minecraft/client/gui/inventory/GuiContainer.doubleClick : Z
   L7
    LINENUMBER 365 L7
    ALOAD 0
    ICONST_0
    PUTFIELD net/minecraft/client/gui/inventory/GuiContainer.ignoreMouseUp : Z
   L8
    LINENUMBER 367 L8
    ILOAD 3
    IFEQ L9
    ILOAD 3
    ICONST_1
    IF_ICMPEQ L9
    ILOAD 4
    IFEQ L10
   L9
    LINENUMBER 369 L9
   FRAME FULL [net/minecraft/client/gui/inventory/GuiContainer I I I I net/minecraft/inventory/Slot J] []
    ALOAD 0
    GETFIELD net/minecraft/client/gui/inventory/GuiContainer.guiLeft : I
    ISTORE 8
   L11
    LINENUMBER 370 L11
    ALOAD 0
    GETFIELD net/minecraft/client/gui/inventory/GuiContainer.guiTop : I
    ISTORE 9
   L12
    LINENUMBER 371 L12
    ILOAD 1
    ILOAD 8
    IF_ICMPLT L13
    ILOAD 2
    ILOAD 9
    IF_ICMPLT L13
    ILOAD 1
    ILOAD 8
    ALOAD 0
    GETFIELD net/minecraft/client/gui/inventory/GuiContainer.xSize : I
    IADD
    IF_ICMPGE L13
    ILOAD 2
    ILOAD 9
    ALOAD 0
    GETFIELD net/minecraft/client/gui/inventory/GuiContainer.ySize : I
    IADD
    IF_ICMPLT L14
   L13
   FRAME FULL [net/minecraft/client/gui/inventory/GuiContainer I I I I net/minecraft/inventory/Slot J I I] []
    ICONST_1
    GOTO L15
   L14
   FRAME FULL [net/minecraft/client/gui/inventory/GuiContainer I I I I net/minecraft/inventory/Slot J I I] []
    ICONST_0
   L15
   FRAME FULL [net/minecraft/client/gui/inventory/GuiContainer I I I I net/minecraft/inventory/Slot J I I] [I]
    ISTORE 10
   L16
    LINENUMBER 372 L16
    ALOAD 5
    IFNULL L17
    ICONST_0
    ISTORE 10
   L17
    LINENUMBER 373 L17
   FRAME FULL [net/minecraft/client/gui/inventory/GuiContainer I I I I net/minecraft/inventory/Slot J I I I] []
    ICONST_M1
    ISTORE 11
   L18
    LINENUMBER 375 L18
    ALOAD 5
    IFNULL L19
   L20
    LINENUMBER 377 L20
    ALOAD 5
    GETFIELD net/minecraft/inventory/Slot.slotNumber : I
    ISTORE 11
   L19
    LINENUMBER 380 L19
   FRAME FULL [net/minecraft/client/gui/inventory/GuiContainer I I I I net/minecraft/inventory/Slot J I I I I] []
    ILOAD 10
    IFEQ L21
   L22
    LINENUMBER 382 L22
    SIPUSH -999
    ISTORE 11
   L21
    LINENUMBER 385 L21
   FRAME FULL [net/minecraft/client/gui/inventory/GuiContainer I I I I net/minecraft/inventory/Slot J I I I I] []
    ALOAD 0
    GETFIELD net/minecraft/client/gui/inventory/GuiContainer.mc : Lnet/minecraft/client/Minecraft;
    GETFIELD net/minecraft/client/Minecraft.gameSettings : Lnet/minecraft/client/settings/GameSettings;
    GETFIELD net/minecraft/client/settings/GameSettings.touchscreen : Z
    IFEQ L23
    ILOAD 10
    IFEQ L23
    ALOAD 0
    GETFIELD net/minecraft/client/gui/inventory/GuiContainer.mc : Lnet/minecraft/client/Minecraft;
    GETFIELD net/minecraft/client/Minecraft.player : Lnet/minecraft/client/entity/EntityPlayerSP;
    GETFIELD net/minecraft/client/entity/EntityPlayerSP.inventory : Lnet/minecraft/entity/player/InventoryPlayer;
    INVOKEVIRTUAL net/minecraft/entity/player/InventoryPlayer.getItemStack ()Lnet/minecraft/item/ItemStack;
    INVOKEVIRTUAL net/minecraft/item/ItemStack.isEmpty ()Z
    IFEQ L23
   L24
    LINENUMBER 387 L24
    ALOAD 0
    GETFIELD net/minecraft/client/gui/inventory/GuiContainer.mc : Lnet/minecraft/client/Minecraft;
    ACONST_NULL
    CHECKCAST net/minecraft/client/gui/GuiScreen
    INVOKEVIRTUAL net/minecraft/client/Minecraft.displayGuiScreen (Lnet/minecraft/client/gui/GuiScreen;)V
   L25
    LINENUMBER 388 L25
    RETURN
   L23
    LINENUMBER 391 L23
   FRAME FULL [net/minecraft/client/gui/inventory/GuiContainer I I I I net/minecraft/inventory/Slot J I I I I] []
    ILOAD 11
    ICONST_M1
    IF_ICMPEQ L10
   L26
    LINENUMBER 393 L26
    ALOAD 0
    GETFIELD net/minecraft/client/gui/inventory/GuiContainer.mc : Lnet/minecraft/client/Minecraft;
    GETFIELD net/minecraft/client/Minecraft.gameSettings : Lnet/minecraft/client/settings/GameSettings;
    GETFIELD net/minecraft/client/settings/GameSettings.touchscreen : Z
    IFEQ L27
   L28
    LINENUMBER 395 L28
    ALOAD 5
    IFNULL L29
    ALOAD 5
    INVOKEVIRTUAL net/minecraft/inventory/Slot.getHasStack ()Z
    IFEQ L29
   L30
    LINENUMBER 397 L30
    ALOAD 0
    ALOAD 5
    PUTFIELD net/minecraft/client/gui/inventory/GuiContainer.clickedSlot : Lnet/minecraft/inventory/Slot;
   L31
    LINENUMBER 398 L31
    ALOAD 0
    GETSTATIC net/minecraft/item/ItemStack.EMPTY : Lnet/minecraft/item/ItemStack;
    PUTFIELD net/minecraft/client/gui/inventory/GuiContainer.draggedStack : Lnet/minecraft/item/ItemStack;
   L32
    LINENUMBER 399 L32
    ALOAD 0
    ILOAD 3
    ICONST_1
    IF_ICMPNE L33
    ICONST_1
    GOTO L34
   L33
   FRAME FULL [net/minecraft/client/gui/inventory/GuiContainer I I I I net/minecraft/inventory/Slot J I I I I] [net/minecraft/client/gui/inventory/GuiContainer]
    ICONST_0
   L34
   FRAME FULL [net/minecraft/client/gui/inventory/GuiContainer I I I I net/minecraft/inventory/Slot J I I I I] [net/minecraft/client/gui/inventory/GuiContainer I]
    PUTFIELD net/minecraft/client/gui/inventory/GuiContainer.isRightMouseClick : Z
    GOTO L10
   L29
    LINENUMBER 403 L29
   FRAME FULL [net/minecraft/client/gui/inventory/GuiContainer I I I I net/minecraft/inventory/Slot J I I I I] []
    ALOAD 0
    ACONST_NULL
    PUTFIELD net/minecraft/client/gui/inventory/GuiContainer.clickedSlot : Lnet/minecraft/inventory/Slot;
    GOTO L10
   L27
    LINENUMBER 406 L27
   FRAME FULL [net/minecraft/client/gui/inventory/GuiContainer I I I I net/minecraft/inventory/Slot J I I I I] []
    ALOAD 0
    GETFIELD net/minecraft/client/gui/inventory/GuiContainer.dragSplitting : Z
    IFNE L10
   L35
    LINENUMBER 408 L35
    ALOAD 0
    GETFIELD net/minecraft/client/gui/inventory/GuiContainer.mc : Lnet/minecraft/client/Minecraft;
    GETFIELD net/minecraft/client/Minecraft.player : Lnet/minecraft/client/entity/EntityPlayerSP;
    GETFIELD net/minecraft/client/entity/EntityPlayerSP.inventory : Lnet/minecraft/entity/player/InventoryPlayer;
    INVOKEVIRTUAL net/minecraft/entity/player/InventoryPlayer.getItemStack ()Lnet/minecraft/item/ItemStack;
    INVOKEVIRTUAL net/minecraft/item/ItemStack.isEmpty ()Z
    IFEQ L36
   L37
    LINENUMBER 410 L37
    ALOAD 0
    GETFIELD net/minecraft/client/gui/inventory/GuiContainer.mc : Lnet/minecraft/client/Minecraft;
    GETFIELD net/minecraft/client/Minecraft.gameSettings : Lnet/minecraft/client/settings/GameSettings;
    GETFIELD net/minecraft/client/settings/GameSettings.keyBindPickBlock : Lnet/minecraft/client/settings/KeyBinding;
    ILOAD 3
    BIPUSH 100
    ISUB
    INVOKEVIRTUAL net/minecraft/client/settings/KeyBinding.isActiveAndMatches (I)Z
    IFEQ L38
   L39
    LINENUMBER 412 L39
    ALOAD 0
    ALOAD 5
    ILOAD 11
    ILOAD 3
    GETSTATIC net/minecraft/inventory/ClickType.CLONE : Lnet/minecraft/inventory/ClickType;
    INVOKEVIRTUAL net/minecraft/client/gui/inventory/GuiContainer.handleMouseClick (Lnet/minecraft/inventory/Slot;IILnet/minecraft/inventory/ClickType;)V
    GOTO L40
   L38
    LINENUMBER 416 L38
   FRAME FULL [net/minecraft/client/gui/inventory/GuiContainer I I I I net/minecraft/inventory/Slot J I I I I] []
    ILOAD 11
    SIPUSH -999
    IF_ICMPEQ L41
    BIPUSH 42
    INVOKESTATIC org/lwjgl/input/Keyboard.isKeyDown (I)Z
    IFNE L42
    BIPUSH 54
    INVOKESTATIC org/lwjgl/input/Keyboard.isKeyDown (I)Z
    IFEQ L41
   L42
   FRAME FULL [net/minecraft/client/gui/inventory/GuiContainer I I I I net/minecraft/inventory/Slot J I I I I] []
    ICONST_1
    GOTO L43
   L41
   FRAME FULL [net/minecraft/client/gui/inventory/GuiContainer I I I I net/minecraft/inventory/Slot J I I I I] []
    ICONST_0
   L43
   FRAME FULL [net/minecraft/client/gui/inventory/GuiContainer I I I I net/minecraft/inventory/Slot J I I I I] [I]
    ISTORE 12
   L44
    LINENUMBER 417 L44
    GETSTATIC net/minecraft/inventory/ClickType.PICKUP : Lnet/minecraft/inventory/ClickType;
    ASTORE 13
   L45
    LINENUMBER 419 L45
    ILOAD 12
    IFEQ L46
   L47
    LINENUMBER 421 L47
    ALOAD 0
    ALOAD 5
    IFNULL L48
    ALOAD 5
    INVOKEVIRTUAL net/minecraft/inventory/Slot.getHasStack ()Z
    IFEQ L48
    ALOAD 5
    INVOKEVIRTUAL net/minecraft/inventory/Slot.getStack ()Lnet/minecraft/item/ItemStack;
    INVOKEVIRTUAL net/minecraft/item/ItemStack.copy ()Lnet/minecraft/item/ItemStack;
    GOTO L49
   L48
   FRAME FULL [net/minecraft/client/gui/inventory/GuiContainer I I I I net/minecraft/inventory/Slot J I I I I I net/minecraft/inventory/ClickType] [net/minecraft/client/gui/inventory/GuiContainer]
    GETSTATIC net/minecraft/item/ItemStack.EMPTY : Lnet/minecraft/item/ItemStack;
   L49
   FRAME FULL [net/minecraft/client/gui/inventory/GuiContainer I I I I net/minecraft/inventory/Slot J I I I I I net/minecraft/inventory/ClickType] [net/minecraft/client/gui/inventory/GuiContainer net/minecraft/item/ItemStack]
    PUTFIELD net/minecraft/client/gui/inventory/GuiContainer.shiftClickedSlot : Lnet/minecraft/item/ItemStack;
   L50
    LINENUMBER 422 L50
    GETSTATIC net/minecraft/inventory/ClickType.QUICK_MOVE : Lnet/minecraft/inventory/ClickType;
    ASTORE 13
    GOTO L51
   L46
    LINENUMBER 424 L46
   FRAME FULL [net/minecraft/client/gui/inventory/GuiContainer I I I I net/minecraft/inventory/Slot J I I I I I net/minecraft/inventory/ClickType] []
    ILOAD 11
    SIPUSH -999
    IF_ICMPNE L51
   L52
    LINENUMBER 426 L52
    GETSTATIC net/minecraft/inventory/ClickType.THROW : Lnet/minecraft/inventory/ClickType;
    ASTORE 13
   L51
    LINENUMBER 429 L51
   FRAME FULL [net/minecraft/client/gui/inventory/GuiContainer I I I I net/minecraft/inventory/Slot J I I I I I net/minecraft/inventory/ClickType] []
    ALOAD 0
    ALOAD 5
    ILOAD 11
    ILOAD 3
    ALOAD 13
    INVOKEVIRTUAL net/minecraft/client/gui/inventory/GuiContainer.handleMouseClick (Lnet/minecraft/inventory/Slot;IILnet/minecraft/inventory/ClickType;)V
   L40
    LINENUMBER 432 L40
   FRAME FULL [net/minecraft/client/gui/inventory/GuiContainer I I I I net/minecraft/inventory/Slot J I I I I] []
    ALOAD 0
    ICONST_1
    PUTFIELD net/minecraft/client/gui/inventory/GuiContainer.ignoreMouseUp : Z
    GOTO L10
   L36
    LINENUMBER 436 L36
   FRAME FULL [net/minecraft/client/gui/inventory/GuiContainer I I I I net/minecraft/inventory/Slot J I I I I] []
    ALOAD 0
    ICONST_1
    PUTFIELD net/minecraft/client/gui/inventory/GuiContainer.dragSplitting : Z
   L53
    LINENUMBER 437 L53
    ALOAD 0
    ILOAD 3
    PUTFIELD net/minecraft/client/gui/inventory/GuiContainer.dragSplittingButton : I
   L54
    LINENUMBER 438 L54
    ALOAD 0
    GETFIELD net/minecraft/client/gui/inventory/GuiContainer.dragSplittingSlots : Ljava/util/Set;
    INVOKEINTERFACE java/util/Set.clear ()V
   L55
    LINENUMBER 440 L55
    ILOAD 3
    IFNE L56
   L57
    LINENUMBER 442 L57
    ALOAD 0
    ICONST_0
    PUTFIELD net/minecraft/client/gui/inventory/GuiContainer.dragSplittingLimit : I
    GOTO L10
   L56
    LINENUMBER 444 L56
   FRAME FULL [net/minecraft/client/gui/inventory/GuiContainer I I I I net/minecraft/inventory/Slot J I I I I] []
    ILOAD 3
    ICONST_1
    IF_ICMPNE L58
   L59
    LINENUMBER 446 L59
    ALOAD 0
    ICONST_1
    PUTFIELD net/minecraft/client/gui/inventory/GuiContainer.dragSplittingLimit : I
    GOTO L10
   L58
    LINENUMBER 448 L58
   FRAME FULL [net/minecraft/client/gui/inventory/GuiContainer I I I I net/minecraft/inventory/Slot J I I I I] []
    ALOAD 0
    GETFIELD net/minecraft/client/gui/inventory/GuiContainer.mc : Lnet/minecraft/client/Minecraft;
    GETFIELD net/minecraft/client/Minecraft.gameSettings : Lnet/minecraft/client/settings/GameSettings;
    GETFIELD net/minecraft/client/settings/GameSettings.keyBindPickBlock : Lnet/minecraft/client/settings/KeyBinding;
    ILOAD 3
    BIPUSH 100
    ISUB
    INVOKEVIRTUAL net/minecraft/client/settings/KeyBinding.isActiveAndMatches (I)Z
    IFEQ L10
   L60
    LINENUMBER 450 L60
    ALOAD 0
    ICONST_2
    PUTFIELD net/minecraft/client/gui/inventory/GuiContainer.dragSplittingLimit : I
   L10
    LINENUMBER 457 L10
   FRAME FULL [net/minecraft/client/gui/inventory/GuiContainer I I I I net/minecraft/inventory/Slot J] []
    ALOAD 0
    ALOAD 5
    PUTFIELD net/minecraft/client/gui/inventory/GuiContainer.lastClickSlot : Lnet/minecraft/inventory/Slot;
   L61
    LINENUMBER 458 L61
    ALOAD 0
    LLOAD 6
    PUTFIELD net/minecraft/client/gui/inventory/GuiContainer.lastClickTime : J
   L62
    LINENUMBER 459 L62
    ALOAD 0
    ILOAD 3
    PUTFIELD net/minecraft/client/gui/inventory/GuiContainer.lastClickButton : I
   L63
    LINENUMBER 460 L63
    RETURN
   L64
    LOCALVARIABLE flag2 Z L44 L40 12
    LOCALVARIABLE clicktype Lnet/minecraft/inventory/ClickType; L45 L40 13
    LOCALVARIABLE j I L11 L10 8
    LOCALVARIABLE k I L12 L10 9
    LOCALVARIABLE flag1 Z L16 L10 10
    LOCALVARIABLE l I L18 L10 11
    LOCALVARIABLE this Lnet/minecraft/client/gui/inventory/GuiContainer; L0 L64 0
    LOCALVARIABLE mouseX I L0 L64 1
    LOCALVARIABLE mouseY I L0 L64 2
    LOCALVARIABLE mouseButton I L0 L64 3
    LOCALVARIABLE flag Z L2 L64 4
    LOCALVARIABLE slot Lnet/minecraft/inventory/Slot; L3 L64 5
    LOCALVARIABLE i J L4 L64 6
    MAXSTACK = 5
    MAXLOCALS = 14

  // access flags 0x4
  protected mouseClickMove(IIIJ)V
   L0
    LINENUMBER 468 L0
    ALOAD 0
    ILOAD 1
    ILOAD 2
    INVOKESPECIAL net/minecraft/client/gui/inventory/GuiContainer.getSlotAtPosition (II)Lnet/minecraft/inventory/Slot;
    ASTORE 6
   L1
    LINENUMBER 469 L1
    ALOAD 0
    GETFIELD net/minecraft/client/gui/inventory/GuiContainer.mc : Lnet/minecraft/client/Minecraft;
    GETFIELD net/minecraft/client/Minecraft.player : Lnet/minecraft/client/entity/EntityPlayerSP;
    GETFIELD net/minecraft/client/entity/EntityPlayerSP.inventory : Lnet/minecraft/entity/player/InventoryPlayer;
    INVOKEVIRTUAL net/minecraft/entity/player/InventoryPlayer.getItemStack ()Lnet/minecraft/item/ItemStack;
    ASTORE 7
   L2
    LINENUMBER 471 L2
    ALOAD 0
    GETFIELD net/minecraft/client/gui/inventory/GuiContainer.clickedSlot : Lnet/minecraft/inventory/Slot;
    IFNULL L3
    ALOAD 0
    GETFIELD net/minecraft/client/gui/inventory/GuiContainer.mc : Lnet/minecraft/client/Minecraft;
    GETFIELD net/minecraft/client/Minecraft.gameSettings : Lnet/minecraft/client/settings/GameSettings;
    GETFIELD net/minecraft/client/settings/GameSettings.touchscreen : Z
    IFEQ L3
   L4
    LINENUMBER 473 L4
    ILOAD 3
    IFEQ L5
    ILOAD 3
    ICONST_1
    IF_ICMPNE L6
   L5
    LINENUMBER 475 L5
   FRAME FULL [net/minecraft/client/gui/inventory/GuiContainer I I I J net/minecraft/inventory/Slot net/minecraft/item/ItemStack] []
    ALOAD 0
    GETFIELD net/minecraft/client/gui/inventory/GuiContainer.draggedStack : Lnet/minecraft/item/ItemStack;
    INVOKEVIRTUAL net/minecraft/item/ItemStack.isEmpty ()Z
    IFEQ L7
   L8
    LINENUMBER 477 L8
    ALOAD 6
    ALOAD 0
    GETFIELD net/minecraft/client/gui/inventory/GuiContainer.clickedSlot : Lnet/minecraft/inventory/Slot;
    IF_ACMPEQ L6
    ALOAD 0
    GETFIELD net/minecraft/client/gui/inventory/GuiContainer.clickedSlot : Lnet/minecraft/inventory/Slot;
    INVOKEVIRTUAL net/minecraft/inventory/Slot.getStack ()Lnet/minecraft/item/ItemStack;
    INVOKEVIRTUAL net/minecraft/item/ItemStack.isEmpty ()Z
    IFNE L6
   L9
    LINENUMBER 479 L9
    ALOAD 0
    ALOAD 0
    GETFIELD net/minecraft/client/gui/inventory/GuiContainer.clickedSlot : Lnet/minecraft/inventory/Slot;
    INVOKEVIRTUAL net/minecraft/inventory/Slot.getStack ()Lnet/minecraft/item/ItemStack;
    INVOKEVIRTUAL net/minecraft/item/ItemStack.copy ()Lnet/minecraft/item/ItemStack;
    PUTFIELD net/minecraft/client/gui/inventory/GuiContainer.draggedStack : Lnet/minecraft/item/ItemStack;
    GOTO L6
   L7
    LINENUMBER 482 L7
   FRAME FULL [net/minecraft/client/gui/inventory/GuiContainer I I I J net/minecraft/inventory/Slot net/minecraft/item/ItemStack] []
    ALOAD 0
    GETFIELD net/minecraft/client/gui/inventory/GuiContainer.draggedStack : Lnet/minecraft/item/ItemStack;
    INVOKEVIRTUAL net/minecraft/item/ItemStack.getCount ()I
    ICONST_1
    IF_ICMPLE L6
    ALOAD 6
    IFNULL L6
    ALOAD 6
    ALOAD 0
    GETFIELD net/minecraft/client/gui/inventory/GuiContainer.draggedStack : Lnet/minecraft/item/ItemStack;
    ICONST_0
    INVOKESTATIC net/minecraft/inventory/Container.canAddItemToSlot (Lnet/minecraft/inventory/Slot;Lnet/minecraft/item/ItemStack;Z)Z
    IFEQ L6
   L10
    LINENUMBER 484 L10
    INVOKESTATIC net/minecraft/client/Minecraft.getSystemTime ()J
    LSTORE 8
   L11
    LINENUMBER 486 L11
    ALOAD 0
    GETFIELD net/minecraft/client/gui/inventory/GuiContainer.currentDragTargetSlot : Lnet/minecraft/inventory/Slot;
    ALOAD 6
    IF_ACMPNE L12
   L13
    LINENUMBER 488 L13
    LLOAD 8
    ALOAD 0
    GETFIELD net/minecraft/client/gui/inventory/GuiContainer.dragItemDropDelay : J
    LSUB
    LDC 500
    LCMP
    IFLE L14
   L15
    LINENUMBER 490 L15
    ALOAD 0
    ALOAD 0
    GETFIELD net/minecraft/client/gui/inventory/GuiContainer.clickedSlot : Lnet/minecraft/inventory/Slot;
    ALOAD 0
    GETFIELD net/minecraft/client/gui/inventory/GuiContainer.clickedSlot : Lnet/minecraft/inventory/Slot;
    GETFIELD net/minecraft/inventory/Slot.slotNumber : I
    ICONST_0
    GETSTATIC net/minecraft/inventory/ClickType.PICKUP : Lnet/minecraft/inventory/ClickType;
    INVOKEVIRTUAL net/minecraft/client/gui/inventory/GuiContainer.handleMouseClick (Lnet/minecraft/inventory/Slot;IILnet/minecraft/inventory/ClickType;)V
   L16
    LINENUMBER 491 L16
    ALOAD 0
    ALOAD 6
    ALOAD 6
    GETFIELD net/minecraft/inventory/Slot.slotNumber : I
    ICONST_1
    GETSTATIC net/minecraft/inventory/ClickType.PICKUP : Lnet/minecraft/inventory/ClickType;
    INVOKEVIRTUAL net/minecraft/client/gui/inventory/GuiContainer.handleMouseClick (Lnet/minecraft/inventory/Slot;IILnet/minecraft/inventory/ClickType;)V
   L17
    LINENUMBER 492 L17
    ALOAD 0
    ALOAD 0
    GETFIELD net/minecraft/client/gui/inventory/GuiContainer.clickedSlot : Lnet/minecraft/inventory/Slot;
    ALOAD 0
    GETFIELD net/minecraft/client/gui/inventory/GuiContainer.clickedSlot : Lnet/minecraft/inventory/Slot;
    GETFIELD net/minecraft/inventory/Slot.slotNumber : I
    ICONST_0
    GETSTATIC net/minecraft/inventory/ClickType.PICKUP : Lnet/minecraft/inventory/ClickType;
    INVOKEVIRTUAL net/minecraft/client/gui/inventory/GuiContainer.handleMouseClick (Lnet/minecraft/inventory/Slot;IILnet/minecraft/inventory/ClickType;)V
   L18
    LINENUMBER 493 L18
    ALOAD 0
    LLOAD 8
    LDC 750
    LADD
    PUTFIELD net/minecraft/client/gui/inventory/GuiContainer.dragItemDropDelay : J
   L19
    LINENUMBER 494 L19
    ALOAD 0
    GETFIELD net/minecraft/client/gui/inventory/GuiContainer.draggedStack : Lnet/minecraft/item/ItemStack;
    ICONST_1
    INVOKEVIRTUAL net/minecraft/item/ItemStack.shrink (I)V
    GOTO L14
   L12
    LINENUMBER 499 L12
   FRAME FULL [net/minecraft/client/gui/inventory/GuiContainer I I I J net/minecraft/inventory/Slot net/minecraft/item/ItemStack J] []
    ALOAD 0
    ALOAD 6
    PUTFIELD net/minecraft/client/gui/inventory/GuiContainer.currentDragTargetSlot : Lnet/minecraft/inventory/Slot;
   L20
    LINENUMBER 500 L20
    ALOAD 0
    LLOAD 8
    PUTFIELD net/minecraft/client/gui/inventory/GuiContainer.dragItemDropDelay : J
   L14
    LINENUMBER 502 L14
   FRAME FULL [net/minecraft/client/gui/inventory/GuiContainer I I I J net/minecraft/inventory/Slot net/minecraft/item/ItemStack J] []
    GOTO L6
   L3
    LINENUMBER 505 L3
   FRAME FULL [net/minecraft/client/gui/inventory/GuiContainer I I I J net/minecraft/inventory/Slot net/minecraft/item/ItemStack] []
    ALOAD 0
    GETFIELD net/minecraft/client/gui/inventory/GuiContainer.dragSplitting : Z
    IFEQ L6
    ALOAD 6
    IFNULL L6
    ALOAD 7
    INVOKEVIRTUAL net/minecraft/item/ItemStack.isEmpty ()Z
    IFNE L6
    ALOAD 7
    INVOKEVIRTUAL net/minecraft/item/ItemStack.getCount ()I
    ALOAD 0
    GETFIELD net/minecraft/client/gui/inventory/GuiContainer.dragSplittingSlots : Ljava/util/Set;
    INVOKEINTERFACE java/util/Set.size ()I
    IF_ICMPGT L21
    ALOAD 0
    GETFIELD net/minecraft/client/gui/inventory/GuiContainer.dragSplittingLimit : I
    ICONST_2
    IF_ICMPNE L6
   L21
   FRAME FULL [net/minecraft/client/gui/inventory/GuiContainer I I I J net/minecraft/inventory/Slot net/minecraft/item/ItemStack] []
    ALOAD 6
    ALOAD 7
    ICONST_1
    INVOKESTATIC net/minecraft/inventory/Container.canAddItemToSlot (Lnet/minecraft/inventory/Slot;Lnet/minecraft/item/ItemStack;Z)Z
    IFEQ L6
    ALOAD 6
    ALOAD 7
    INVOKEVIRTUAL net/minecraft/inventory/Slot.isItemValid (Lnet/minecraft/item/ItemStack;)Z
    IFEQ L6
    ALOAD 0
    GETFIELD net/minecraft/client/gui/inventory/GuiContainer.inventorySlots : Lnet/minecraft/inventory/Container;
    ALOAD 6
    INVOKEVIRTUAL net/minecraft/inventory/Container.canDragIntoSlot (Lnet/minecraft/inventory/Slot;)Z
    IFEQ L6
   L22
    LINENUMBER 507 L22
    ALOAD 0
    GETFIELD net/minecraft/client/gui/inventory/GuiContainer.dragSplittingSlots : Ljava/util/Set;
    ALOAD 6
    INVOKEINTERFACE java/util/Set.add (Ljava/lang/Object;)Z
    POP
   L23
    LINENUMBER 508 L23
    ALOAD 0
    INVOKESPECIAL net/minecraft/client/gui/inventory/GuiContainer.updateDragSplitting ()V
   L6
    LINENUMBER 510 L6
   FRAME FULL [net/minecraft/client/gui/inventory/GuiContainer I I I J net/minecraft/inventory/Slot net/minecraft/item/ItemStack] []
    RETURN
   L24
    LOCALVARIABLE i J L11 L14 8
    LOCALVARIABLE this Lnet/minecraft/client/gui/inventory/GuiContainer; L0 L24 0
    LOCALVARIABLE mouseX I L0 L24 1
    LOCALVARIABLE mouseY I L0 L24 2
    LOCALVARIABLE clickedMouseButton I L0 L24 3
    LOCALVARIABLE timeSinceLastClick J L0 L24 4
    LOCALVARIABLE slot Lnet/minecraft/inventory/Slot; L1 L24 6
    LOCALVARIABLE itemstack Lnet/minecraft/item/ItemStack; L2 L24 7
    MAXSTACK = 5
    MAXLOCALS = 10

  // access flags 0x4
  protected mouseReleased(III)V
   L0
    LINENUMBER 517 L0
    ALOAD 0
    ILOAD 1
    ILOAD 2
    ILOAD 3
    INVOKESPECIAL net/minecraft/client/gui/GuiScreen.mouseReleased (III)V
   L1
    LINENUMBER 518 L1
    ALOAD 0
    ILOAD 1
    ILOAD 2
    INVOKESPECIAL net/minecraft/client/gui/inventory/GuiContainer.getSlotAtPosition (II)Lnet/minecraft/inventory/Slot;
    ASTORE 4
   L2
    LINENUMBER 519 L2
    ALOAD 0
    GETFIELD net/minecraft/client/gui/inventory/GuiContainer.guiLeft : I
    ISTORE 5
   L3
    LINENUMBER 520 L3
    ALOAD 0
    GETFIELD net/minecraft/client/gui/inventory/GuiContainer.guiTop : I
    ISTORE 6
   L4
    LINENUMBER 521 L4
    ILOAD 1
    ILOAD 5
    IF_ICMPLT L5
    ILOAD 2
    ILOAD 6
    IF_ICMPLT L5
    ILOAD 1
    ILOAD 5
    ALOAD 0
    GETFIELD net/minecraft/client/gui/inventory/GuiContainer.xSize : I
    IADD
    IF_ICMPGE L5
    ILOAD 2
    ILOAD 6
    ALOAD 0
    GETFIELD net/minecraft/client/gui/inventory/GuiContainer.ySize : I
    IADD
    IF_ICMPLT L6
   L5
   FRAME FULL [net/minecraft/client/gui/inventory/GuiContainer I I I net/minecraft/inventory/Slot I I] []
    ICONST_1
    GOTO L7
   L6
   FRAME FULL [net/minecraft/client/gui/inventory/GuiContainer I I I net/minecraft/inventory/Slot I I] []
    ICONST_0
   L7
   FRAME FULL [net/minecraft/client/gui/inventory/GuiContainer I I I net/minecraft/inventory/Slot I I] [I]
    ISTORE 7
   L8
    LINENUMBER 522 L8
    ALOAD 4
    IFNULL L9
    ICONST_0
    ISTORE 7
   L9
    LINENUMBER 523 L9
   FRAME FULL [net/minecraft/client/gui/inventory/GuiContainer I I I net/minecraft/inventory/Slot I I I] []
    ICONST_M1
    ISTORE 8
   L10
    LINENUMBER 525 L10
    ALOAD 4
    IFNULL L11
   L12
    LINENUMBER 527 L12
    ALOAD 4
    GETFIELD net/minecraft/inventory/Slot.slotNumber : I
    ISTORE 8
   L11
    LINENUMBER 530 L11
   FRAME FULL [net/minecraft/client/gui/inventory/GuiContainer I I I net/minecraft/inventory/Slot I I I I] []
    ILOAD 7
    IFEQ L13
   L14
    LINENUMBER 532 L14
    SIPUSH -999
    ISTORE 8
   L13
    LINENUMBER 535 L13
   FRAME FULL [net/minecraft/client/gui/inventory/GuiContainer I I I net/minecraft/inventory/Slot I I I I] []
    ALOAD 0
    GETFIELD net/minecraft/client/gui/inventory/GuiContainer.doubleClick : Z
    IFEQ L15
    ALOAD 4
    IFNULL L15
    ILOAD 3
    IFNE L15
    ALOAD 0
    GETFIELD net/minecraft/client/gui/inventory/GuiContainer.inventorySlots : Lnet/minecraft/inventory/Container;
    GETSTATIC net/minecraft/item/ItemStack.EMPTY : Lnet/minecraft/item/ItemStack;
    ALOAD 4
    INVOKEVIRTUAL net/minecraft/inventory/Container.canMergeSlot (Lnet/minecraft/item/ItemStack;Lnet/minecraft/inventory/Slot;)Z
    IFEQ L15
   L16
    LINENUMBER 537 L16
    INVOKESTATIC net/minecraft/client/gui/inventory/GuiContainer.isShiftKeyDown ()Z
    IFEQ L17
   L18
    LINENUMBER 539 L18
    ALOAD 0
    GETFIELD net/minecraft/client/gui/inventory/GuiContainer.shiftClickedSlot : Lnet/minecraft/item/ItemStack;
    INVOKEVIRTUAL net/minecraft/item/ItemStack.isEmpty ()Z
    IFNE L19
   L20
    LINENUMBER 541 L20
    ALOAD 0
    GETFIELD net/minecraft/client/gui/inventory/GuiContainer.inventorySlots : Lnet/minecraft/inventory/Container;
    GETFIELD net/minecraft/inventory/Container.inventorySlots : Ljava/util/List;
    INVOKEINTERFACE java/util/List.iterator ()Ljava/util/Iterator;
    ASTORE 9
   L21
   FRAME FULL [net/minecraft/client/gui/inventory/GuiContainer I I I net/minecraft/inventory/Slot I I I I java/util/Iterator] []
    ALOAD 9
    INVOKEINTERFACE java/util/Iterator.hasNext ()Z
    IFEQ L22
    ALOAD 9
    INVOKEINTERFACE java/util/Iterator.next ()Ljava/lang/Object;
    CHECKCAST net/minecraft/inventory/Slot
    ASTORE 10
   L23
    LINENUMBER 543 L23
    ALOAD 10
    IFNULL L24
    ALOAD 10
    ALOAD 0
    GETFIELD net/minecraft/client/gui/inventory/GuiContainer.mc : Lnet/minecraft/client/Minecraft;
    GETFIELD net/minecraft/client/Minecraft.player : Lnet/minecraft/client/entity/EntityPlayerSP;
    INVOKEVIRTUAL net/minecraft/inventory/Slot.canTakeStack (Lnet/minecraft/entity/player/EntityPlayer;)Z
    IFEQ L24
    ALOAD 10
    INVOKEVIRTUAL net/minecraft/inventory/Slot.getHasStack ()Z
    IFEQ L24
    ALOAD 10
    ALOAD 4
    INVOKEVIRTUAL net/minecraft/inventory/Slot.isSameInventory (Lnet/minecraft/inventory/Slot;)Z
    IFEQ L24
    ALOAD 10
    ALOAD 0
    GETFIELD net/minecraft/client/gui/inventory/GuiContainer.shiftClickedSlot : Lnet/minecraft/item/ItemStack;
    ICONST_1
    INVOKESTATIC net/minecraft/inventory/Container.canAddItemToSlot (Lnet/minecraft/inventory/Slot;Lnet/minecraft/item/ItemStack;Z)Z
    IFEQ L24
   L25
    LINENUMBER 545 L25
    ALOAD 0
    ALOAD 10
    ALOAD 10
    GETFIELD net/minecraft/inventory/Slot.slotNumber : I
    ILOAD 3
    GETSTATIC net/minecraft/inventory/ClickType.QUICK_MOVE : Lnet/minecraft/inventory/ClickType;
    INVOKEVIRTUAL net/minecraft/client/gui/inventory/GuiContainer.handleMouseClick (Lnet/minecraft/inventory/Slot;IILnet/minecraft/inventory/ClickType;)V
   L24
    LINENUMBER 547 L24
   FRAME FULL [net/minecraft/client/gui/inventory/GuiContainer I I I net/minecraft/inventory/Slot I I I I java/util/Iterator net/minecraft/inventory/Slot] []
    GOTO L21
   L22
   FRAME FULL [net/minecraft/client/gui/inventory/GuiContainer I I I net/minecraft/inventory/Slot I I I I java/util/Iterator] []
    GOTO L19
   L17
    LINENUMBER 552 L17
   FRAME FULL [net/minecraft/client/gui/inventory/GuiContainer I I I net/minecraft/inventory/Slot I I I I] []
    ALOAD 0
    ALOAD 4
    ILOAD 8
    ILOAD 3
    GETSTATIC net/minecraft/inventory/ClickType.PICKUP_ALL : Lnet/minecraft/inventory/ClickType;
    INVOKEVIRTUAL net/minecraft/client/gui/inventory/GuiContainer.handleMouseClick (Lnet/minecraft/inventory/Slot;IILnet/minecraft/inventory/ClickType;)V
   L19
    LINENUMBER 555 L19
   FRAME FULL [net/minecraft/client/gui/inventory/GuiContainer I I I net/minecraft/inventory/Slot I I I I] []
    ALOAD 0
    ICONST_0
    PUTFIELD net/minecraft/client/gui/inventory/GuiContainer.doubleClick : Z
   L26
    LINENUMBER 556 L26
    ALOAD 0
    LCONST_0
    PUTFIELD net/minecraft/client/gui/inventory/GuiContainer.lastClickTime : J
    GOTO L27
   L15
    LINENUMBER 560 L15
   FRAME FULL [net/minecraft/client/gui/inventory/GuiContainer I I I net/minecraft/inventory/Slot I I I I] []
    ALOAD 0
    GETFIELD net/minecraft/client/gui/inventory/GuiContainer.dragSplitting : Z
    IFEQ L28
    ALOAD 0
    GETFIELD net/minecraft/client/gui/inventory/GuiContainer.dragSplittingButton : I
    ILOAD 3
    IF_ICMPEQ L28
   L29
    LINENUMBER 562 L29
    ALOAD 0
    ICONST_0
    PUTFIELD net/minecraft/client/gui/inventory/GuiContainer.dragSplitting : Z
   L30
    LINENUMBER 563 L30
    ALOAD 0
    GETFIELD net/minecraft/client/gui/inventory/GuiContainer.dragSplittingSlots : Ljava/util/Set;
    INVOKEINTERFACE java/util/Set.clear ()V
   L31
    LINENUMBER 564 L31
    ALOAD 0
    ICONST_1
    PUTFIELD net/minecraft/client/gui/inventory/GuiContainer.ignoreMouseUp : Z
   L32
    LINENUMBER 565 L32
    RETURN
   L28
    LINENUMBER 568 L28
   FRAME FULL [net/minecraft/client/gui/inventory/GuiContainer I I I net/minecraft/inventory/Slot I I I I] []
    ALOAD 0
    GETFIELD net/minecraft/client/gui/inventory/GuiContainer.ignoreMouseUp : Z
    IFEQ L33
   L34
    LINENUMBER 570 L34
    ALOAD 0
    ICONST_0
    PUTFIELD net/minecraft/client/gui/inventory/GuiContainer.ignoreMouseUp : Z
   L35
    LINENUMBER 571 L35
    RETURN
   L33
    LINENUMBER 574 L33
   FRAME FULL [net/minecraft/client/gui/inventory/GuiContainer I I I net/minecraft/inventory/Slot I I I I] []
    ALOAD 0
    GETFIELD net/minecraft/client/gui/inventory/GuiContainer.clickedSlot : Lnet/minecraft/inventory/Slot;
    IFNULL L36
    ALOAD 0
    GETFIELD net/minecraft/client/gui/inventory/GuiContainer.mc : Lnet/minecraft/client/Minecraft;
    GETFIELD net/minecraft/client/Minecraft.gameSettings : Lnet/minecraft/client/settings/GameSettings;
    GETFIELD net/minecraft/client/settings/GameSettings.touchscreen : Z
    IFEQ L36
   L37
    LINENUMBER 576 L37
    ILOAD 3
    IFEQ L38
    ILOAD 3
    ICONST_1
    IF_ICMPNE L27
   L38
    LINENUMBER 578 L38
   FRAME FULL [net/minecraft/client/gui/inventory/GuiContainer I I I net/minecraft/inventory/Slot I I I I] []
    ALOAD 0
    GETFIELD net/minecraft/client/gui/inventory/GuiContainer.draggedStack : Lnet/minecraft/item/ItemStack;
    INVOKEVIRTUAL net/minecraft/item/ItemStack.isEmpty ()Z
    IFEQ L39
    ALOAD 4
    ALOAD 0
    GETFIELD net/minecraft/client/gui/inventory/GuiContainer.clickedSlot : Lnet/minecraft/inventory/Slot;
    IF_ACMPEQ L39
   L40
    LINENUMBER 580 L40
    ALOAD 0
    ALOAD 0
    GETFIELD net/minecraft/client/gui/inventory/GuiContainer.clickedSlot : Lnet/minecraft/inventory/Slot;
    INVOKEVIRTUAL net/minecraft/inventory/Slot.getStack ()Lnet/minecraft/item/ItemStack;
    PUTFIELD net/minecraft/client/gui/inventory/GuiContainer.draggedStack : Lnet/minecraft/item/ItemStack;
   L39
    LINENUMBER 583 L39
   FRAME FULL [net/minecraft/client/gui/inventory/GuiContainer I I I net/minecraft/inventory/Slot I I I I] []
    ALOAD 4
    ALOAD 0
    GETFIELD net/minecraft/client/gui/inventory/GuiContainer.draggedStack : Lnet/minecraft/item/ItemStack;
    ICONST_0
    INVOKESTATIC net/minecraft/inventory/Container.canAddItemToSlot (Lnet/minecraft/inventory/Slot;Lnet/minecraft/item/ItemStack;Z)Z
    ISTORE 9
   L41
    LINENUMBER 585 L41
    ILOAD 8
    ICONST_M1
    IF_ICMPEQ L42
    ALOAD 0
    GETFIELD net/minecraft/client/gui/inventory/GuiContainer.draggedStack : Lnet/minecraft/item/ItemStack;
    INVOKEVIRTUAL net/minecraft/item/ItemStack.isEmpty ()Z
    IFNE L42
    ILOAD 9
    IFEQ L42
   L43
    LINENUMBER 587 L43
    ALOAD 0
    ALOAD 0
    GETFIELD net/minecraft/client/gui/inventory/GuiContainer.clickedSlot : Lnet/minecraft/inventory/Slot;
    ALOAD 0
    GETFIELD net/minecraft/client/gui/inventory/GuiContainer.clickedSlot : Lnet/minecraft/inventory/Slot;
    GETFIELD net/minecraft/inventory/Slot.slotNumber : I
    ILOAD 3
    GETSTATIC net/minecraft/inventory/ClickType.PICKUP : Lnet/minecraft/inventory/ClickType;
    INVOKEVIRTUAL net/minecraft/client/gui/inventory/GuiContainer.handleMouseClick (Lnet/minecraft/inventory/Slot;IILnet/minecraft/inventory/ClickType;)V
   L44
    LINENUMBER 588 L44
    ALOAD 0
    ALOAD 4
    ILOAD 8
    ICONST_0
    GETSTATIC net/minecraft/inventory/ClickType.PICKUP : Lnet/minecraft/inventory/ClickType;
    INVOKEVIRTUAL net/minecraft/client/gui/inventory/GuiContainer.handleMouseClick (Lnet/minecraft/inventory/Slot;IILnet/minecraft/inventory/ClickType;)V
   L45
    LINENUMBER 590 L45
    ALOAD 0
    GETFIELD net/minecraft/client/gui/inventory/GuiContainer.mc : Lnet/minecraft/client/Minecraft;
    GETFIELD net/minecraft/client/Minecraft.player : Lnet/minecraft/client/entity/EntityPlayerSP;
    GETFIELD net/minecraft/client/entity/EntityPlayerSP.inventory : Lnet/minecraft/entity/player/InventoryPlayer;
    INVOKEVIRTUAL net/minecraft/entity/player/InventoryPlayer.getItemStack ()Lnet/minecraft/item/ItemStack;
    INVOKEVIRTUAL net/minecraft/item/ItemStack.isEmpty ()Z
    IFEQ L46
   L47
    LINENUMBER 592 L47
    ALOAD 0
    GETSTATIC net/minecraft/item/ItemStack.EMPTY : Lnet/minecraft/item/ItemStack;
    PUTFIELD net/minecraft/client/gui/inventory/GuiContainer.returningStack : Lnet/minecraft/item/ItemStack;
    GOTO L48
   L46
    LINENUMBER 596 L46
   FRAME FULL [net/minecraft/client/gui/inventory/GuiContainer I I I net/minecraft/inventory/Slot I I I I I] []
    ALOAD 0
    ALOAD 0
    GETFIELD net/minecraft/client/gui/inventory/GuiContainer.clickedSlot : Lnet/minecraft/inventory/Slot;
    ALOAD 0
    GETFIELD net/minecraft/client/gui/inventory/GuiContainer.clickedSlot : Lnet/minecraft/inventory/Slot;
    GETFIELD net/minecraft/inventory/Slot.slotNumber : I
    ILOAD 3
    GETSTATIC net/minecraft/inventory/ClickType.PICKUP : Lnet/minecraft/inventory/ClickType;
    INVOKEVIRTUAL net/minecraft/client/gui/inventory/GuiContainer.handleMouseClick (Lnet/minecraft/inventory/Slot;IILnet/minecraft/inventory/ClickType;)V
   L49
    LINENUMBER 597 L49
    ALOAD 0
    ILOAD 1
    ILOAD 5
    ISUB
    PUTFIELD net/minecraft/client/gui/inventory/GuiContainer.touchUpX : I
   L50
    LINENUMBER 598 L50
    ALOAD 0
    ILOAD 2
    ILOAD 6
    ISUB
    PUTFIELD net/minecraft/client/gui/inventory/GuiContainer.touchUpY : I
   L51
    LINENUMBER 599 L51
    ALOAD 0
    ALOAD 0
    GETFIELD net/minecraft/client/gui/inventory/GuiContainer.clickedSlot : Lnet/minecraft/inventory/Slot;
    PUTFIELD net/minecraft/client/gui/inventory/GuiContainer.returningStackDestSlot : Lnet/minecraft/inventory/Slot;
   L52
    LINENUMBER 600 L52
    ALOAD 0
    ALOAD 0
    GETFIELD net/minecraft/client/gui/inventory/GuiContainer.draggedStack : Lnet/minecraft/item/ItemStack;
    PUTFIELD net/minecraft/client/gui/inventory/GuiContainer.returningStack : Lnet/minecraft/item/ItemStack;
   L53
    LINENUMBER 601 L53
    ALOAD 0
    INVOKESTATIC net/minecraft/client/Minecraft.getSystemTime ()J
    PUTFIELD net/minecraft/client/gui/inventory/GuiContainer.returningStackTime : J
    GOTO L48
   L42
    LINENUMBER 604 L42
   FRAME FULL [net/minecraft/client/gui/inventory/GuiContainer I I I net/minecraft/inventory/Slot I I I I I] []
    ALOAD 0
    GETFIELD net/minecraft/client/gui/inventory/GuiContainer.draggedStack : Lnet/minecraft/item/ItemStack;
    INVOKEVIRTUAL net/minecraft/item/ItemStack.isEmpty ()Z
    IFNE L48
   L54
    LINENUMBER 606 L54
    ALOAD 0
    ILOAD 1
    ILOAD 5
    ISUB
    PUTFIELD net/minecraft/client/gui/inventory/GuiContainer.touchUpX : I
   L55
    LINENUMBER 607 L55
    ALOAD 0
    ILOAD 2
    ILOAD 6
    ISUB
    PUTFIELD net/minecraft/client/gui/inventory/GuiContainer.touchUpY : I
   L56
    LINENUMBER 608 L56
    ALOAD 0
    ALOAD 0
    GETFIELD net/minecraft/client/gui/inventory/GuiContainer.clickedSlot : Lnet/minecraft/inventory/Slot;
    PUTFIELD net/minecraft/client/gui/inventory/GuiContainer.returningStackDestSlot : Lnet/minecraft/inventory/Slot;
   L57
    LINENUMBER 609 L57
    ALOAD 0
    ALOAD 0
    GETFIELD net/minecraft/client/gui/inventory/GuiContainer.draggedStack : Lnet/minecraft/item/ItemStack;
    PUTFIELD net/minecraft/client/gui/inventory/GuiContainer.returningStack : Lnet/minecraft/item/ItemStack;
   L58
    LINENUMBER 610 L58
    ALOAD 0
    INVOKESTATIC net/minecraft/client/Minecraft.getSystemTime ()J
    PUTFIELD net/minecraft/client/gui/inventory/GuiContainer.returningStackTime : J
   L48
    LINENUMBER 613 L48
   FRAME FULL [net/minecraft/client/gui/inventory/GuiContainer I I I net/minecraft/inventory/Slot I I I I I] []
    ALOAD 0
    GETSTATIC net/minecraft/item/ItemStack.EMPTY : Lnet/minecraft/item/ItemStack;
    PUTFIELD net/minecraft/client/gui/inventory/GuiContainer.draggedStack : Lnet/minecraft/item/ItemStack;
   L59
    LINENUMBER 614 L59
    ALOAD 0
    ACONST_NULL
    PUTFIELD net/minecraft/client/gui/inventory/GuiContainer.clickedSlot : Lnet/minecraft/inventory/Slot;
   L60
    LINENUMBER 615 L60
    GOTO L27
   L36
    LINENUMBER 617 L36
   FRAME FULL [net/minecraft/client/gui/inventory/GuiContainer I I I net/minecraft/inventory/Slot I I I I] []
    ALOAD 0
    GETFIELD net/minecraft/client/gui/inventory/GuiContainer.dragSplitting : Z
    IFEQ L61
    ALOAD 0
    GETFIELD net/minecraft/client/gui/inventory/GuiContainer.dragSplittingSlots : Ljava/util/Set;
    INVOKEINTERFACE java/util/Set.isEmpty ()Z
    IFNE L61
   L62
    LINENUMBER 619 L62
    ALOAD 0
    ACONST_NULL
    CHECKCAST net/minecraft/inventory/Slot
    SIPUSH -999
    ICONST_0
    ALOAD 0
    GETFIELD net/minecraft/client/gui/inventory/GuiContainer.dragSplittingLimit : I
    INVOKESTATIC net/minecraft/inventory/Container.getQuickcraftMask (II)I
    GETSTATIC net/minecraft/inventory/ClickType.QUICK_CRAFT : Lnet/minecraft/inventory/ClickType;
    INVOKEVIRTUAL net/minecraft/client/gui/inventory/GuiContainer.handleMouseClick (Lnet/minecraft/inventory/Slot;IILnet/minecraft/inventory/ClickType;)V
   L63
    LINENUMBER 621 L63
    ALOAD 0
    GETFIELD net/minecraft/client/gui/inventory/GuiContainer.dragSplittingSlots : Ljava/util/Set;
    INVOKEINTERFACE java/util/Set.iterator ()Ljava/util/Iterator;
    ASTORE 9
   L64
   FRAME FULL [net/minecraft/client/gui/inventory/GuiContainer I I I net/minecraft/inventory/Slot I I I I java/util/Iterator] []
    ALOAD 9
    INVOKEINTERFACE java/util/Iterator.hasNext ()Z
    IFEQ L65
    ALOAD 9
    INVOKEINTERFACE java/util/Iterator.next ()Ljava/lang/Object;
    CHECKCAST net/minecraft/inventory/Slot
    ASTORE 10
   L66
    LINENUMBER 623 L66
    ALOAD 0
    ALOAD 10
    ALOAD 10
    GETFIELD net/minecraft/inventory/Slot.slotNumber : I
    ICONST_1
    ALOAD 0
    GETFIELD net/minecraft/client/gui/inventory/GuiContainer.dragSplittingLimit : I
    INVOKESTATIC net/minecraft/inventory/Container.getQuickcraftMask (II)I
    GETSTATIC net/minecraft/inventory/ClickType.QUICK_CRAFT : Lnet/minecraft/inventory/ClickType;
    INVOKEVIRTUAL net/minecraft/client/gui/inventory/GuiContainer.handleMouseClick (Lnet/minecraft/inventory/Slot;IILnet/minecraft/inventory/ClickType;)V
   L67
    LINENUMBER 624 L67
    GOTO L64
   L65
    LINENUMBER 626 L65
   FRAME FULL [net/minecraft/client/gui/inventory/GuiContainer I I I net/minecraft/inventory/Slot I I I I java/util/Iterator] []
    ALOAD 0
    ACONST_NULL
    CHECKCAST net/minecraft/inventory/Slot
    SIPUSH -999
    ICONST_2
    ALOAD 0
    GETFIELD net/minecraft/client/gui/inventory/GuiContainer.dragSplittingLimit : I
    INVOKESTATIC net/minecraft/inventory/Container.getQuickcraftMask (II)I
    GETSTATIC net/minecraft/inventory/ClickType.QUICK_CRAFT : Lnet/minecraft/inventory/ClickType;
    INVOKEVIRTUAL net/minecraft/client/gui/inventory/GuiContainer.handleMouseClick (Lnet/minecraft/inventory/Slot;IILnet/minecraft/inventory/ClickType;)V
    GOTO L27
   L61
    LINENUMBER 628 L61
   FRAME FULL [net/minecraft/client/gui/inventory/GuiContainer I I I net/minecraft/inventory/Slot I I I I] []
    ALOAD 0
    GETFIELD net/minecraft/client/gui/inventory/GuiContainer.mc : Lnet/minecraft/client/Minecraft;
    GETFIELD net/minecraft/client/Minecraft.player : Lnet/minecraft/client/entity/EntityPlayerSP;
    GETFIELD net/minecraft/client/entity/EntityPlayerSP.inventory : Lnet/minecraft/entity/player/InventoryPlayer;
    INVOKEVIRTUAL net/minecraft/entity/player/InventoryPlayer.getItemStack ()Lnet/minecraft/item/ItemStack;
    INVOKEVIRTUAL net/minecraft/item/ItemStack.isEmpty ()Z
    IFNE L27
   L68
    LINENUMBER 630 L68
    ALOAD 0
    GETFIELD net/minecraft/client/gui/inventory/GuiContainer.mc : Lnet/minecraft/client/Minecraft;
    GETFIELD net/minecraft/client/Minecraft.gameSettings : Lnet/minecraft/client/settings/GameSettings;
    GETFIELD net/minecraft/client/settings/GameSettings.keyBindPickBlock : Lnet/minecraft/client/settings/KeyBinding;
    ILOAD 3
    BIPUSH 100
    ISUB
    INVOKEVIRTUAL net/minecraft/client/settings/KeyBinding.isActiveAndMatches (I)Z
    IFEQ L69
   L70
    LINENUMBER 632 L70
    ALOAD 0
    ALOAD 4
    ILOAD 8
    ILOAD 3
    GETSTATIC net/minecraft/inventory/ClickType.CLONE : Lnet/minecraft/inventory/ClickType;
    INVOKEVIRTUAL net/minecraft/client/gui/inventory/GuiContainer.handleMouseClick (Lnet/minecraft/inventory/Slot;IILnet/minecraft/inventory/ClickType;)V
    GOTO L27
   L69
    LINENUMBER 636 L69
   FRAME FULL [net/minecraft/client/gui/inventory/GuiContainer I I I net/minecraft/inventory/Slot I I I I] []
    ILOAD 8
    SIPUSH -999
    IF_ICMPEQ L71
    BIPUSH 42
    INVOKESTATIC org/lwjgl/input/Keyboard.isKeyDown (I)Z
    IFNE L72
    BIPUSH 54
    INVOKESTATIC org/lwjgl/input/Keyboard.isKeyDown (I)Z
    IFEQ L71
   L72
   FRAME FULL [net/minecraft/client/gui/inventory/GuiContainer I I I net/minecraft/inventory/Slot I I I I] []
    ICONST_1
    GOTO L73
   L71
   FRAME FULL [net/minecraft/client/gui/inventory/GuiContainer I I I net/minecraft/inventory/Slot I I I I] []
    ICONST_0
   L73
   FRAME FULL [net/minecraft/client/gui/inventory/GuiContainer I I I net/minecraft/inventory/Slot I I I I] [I]
    ISTORE 9
   L74
    LINENUMBER 638 L74
    ILOAD 9
    IFEQ L75
   L76
    LINENUMBER 640 L76
    ALOAD 0
    ALOAD 4
    IFNULL L77
    ALOAD 4
    INVOKEVIRTUAL net/minecraft/inventory/Slot.getHasStack ()Z
    IFEQ L77
    ALOAD 4
    INVOKEVIRTUAL net/minecraft/inventory/Slot.getStack ()Lnet/minecraft/item/ItemStack;
    INVOKEVIRTUAL net/minecraft/item/ItemStack.copy ()Lnet/minecraft/item/ItemStack;
    GOTO L78
   L77
   FRAME FULL [net/minecraft/client/gui/inventory/GuiContainer I I I net/minecraft/inventory/Slot I I I I I] [net/minecraft/client/gui/inventory/GuiContainer]
    GETSTATIC net/minecraft/item/ItemStack.EMPTY : Lnet/minecraft/item/ItemStack;
   L78
   FRAME FULL [net/minecraft/client/gui/inventory/GuiContainer I I I net/minecraft/inventory/Slot I I I I I] [net/minecraft/client/gui/inventory/GuiContainer net/minecraft/item/ItemStack]
    PUTFIELD net/minecraft/client/gui/inventory/GuiContainer.shiftClickedSlot : Lnet/minecraft/item/ItemStack;
   L75
    LINENUMBER 643 L75
   FRAME FULL [net/minecraft/client/gui/inventory/GuiContainer I I I net/minecraft/inventory/Slot I I I I I] []
    ALOAD 0
    ALOAD 4
    ILOAD 8
    ILOAD 3
    ILOAD 9
    IFEQ L79
    GETSTATIC net/minecraft/inventory/ClickType.QUICK_MOVE : Lnet/minecraft/inventory/ClickType;
    GOTO L80
   L79
   FRAME FULL [net/minecraft/client/gui/inventory/GuiContainer I I I net/minecraft/inventory/Slot I I I I I] [net/minecraft/client/gui/inventory/GuiContainer net/minecraft/inventory/Slot I I]
    GETSTATIC net/minecraft/inventory/ClickType.PICKUP : Lnet/minecraft/inventory/ClickType;
   L80
   FRAME FULL [net/minecraft/client/gui/inventory/GuiContainer I I I net/minecraft/inventory/Slot I I I I I] [net/minecraft/client/gui/inventory/GuiContainer net/minecraft/inventory/Slot I I net/minecraft/inventory/ClickType]
    INVOKEVIRTUAL net/minecraft/client/gui/inventory/GuiContainer.handleMouseClick (Lnet/minecraft/inventory/Slot;IILnet/minecraft/inventory/ClickType;)V
   L27
    LINENUMBER 648 L27
   FRAME FULL [net/minecraft/client/gui/inventory/GuiContainer I I I net/minecraft/inventory/Slot I I I I] []
    ALOAD 0
    GETFIELD net/minecraft/client/gui/inventory/GuiContainer.mc : Lnet/minecraft/client/Minecraft;
    GETFIELD net/minecraft/client/Minecraft.player : Lnet/minecraft/client/entity/EntityPlayerSP;
    GETFIELD net/minecraft/client/entity/EntityPlayerSP.inventory : Lnet/minecraft/entity/player/InventoryPlayer;
    INVOKEVIRTUAL net/minecraft/entity/player/InventoryPlayer.getItemStack ()Lnet/minecraft/item/ItemStack;
    INVOKEVIRTUAL net/minecraft/item/ItemStack.isEmpty ()Z
    IFEQ L81
   L82
    LINENUMBER 650 L82
    ALOAD 0
    LCONST_0
    PUTFIELD net/minecraft/client/gui/inventory/GuiContainer.lastClickTime : J
   L81
    LINENUMBER 653 L81
   FRAME FULL [net/minecraft/client/gui/inventory/GuiContainer I I I net/minecraft/inventory/Slot I I I I] []
    ALOAD 0
    ICONST_0
    PUTFIELD net/minecraft/client/gui/inventory/GuiContainer.dragSplitting : Z
   L83
    LINENUMBER 654 L83
    RETURN
   L84
    LOCALVARIABLE slot2 Lnet/minecraft/inventory/Slot; L23 L24 10
    LOCALVARIABLE flag2 Z L41 L60 9
    LOCALVARIABLE slot1 Lnet/minecraft/inventory/Slot; L66 L67 10
    LOCALVARIABLE flag1 Z L74 L27 9
    LOCALVARIABLE this Lnet/minecraft/client/gui/inventory/GuiContainer; L0 L84 0
    LOCALVARIABLE mouseX I L0 L84 1
    LOCALVARIABLE mouseY I L0 L84 2
    LOCALVARIABLE state I L0 L84 3
    LOCALVARIABLE slot Lnet/minecraft/inventory/Slot; L2 L84 4
    LOCALVARIABLE i I L3 L84 5
    LOCALVARIABLE j I L4 L84 6
    LOCALVARIABLE flag Z L8 L84 7
    LOCALVARIABLE k I L10 L84 8
    MAXSTACK = 5
    MAXLOCALS = 11

  // access flags 0x2
  private isMouseOverSlot(Lnet/minecraft/inventory/Slot;II)Z
   L0
    LINENUMBER 661 L0
    ALOAD 0
    ALOAD 1
    GETFIELD net/minecraft/inventory/Slot.xPos : I
    ALOAD 1
    GETFIELD net/minecraft/inventory/Slot.yPos : I
    BIPUSH 16
    BIPUSH 16
    ILOAD 2
    ILOAD 3
    INVOKEVIRTUAL net/minecraft/client/gui/inventory/GuiContainer.isPointInRegion (IIIIII)Z
    IRETURN
   L1
    LOCALVARIABLE this Lnet/minecraft/client/gui/inventory/GuiContainer; L0 L1 0
    LOCALVARIABLE slotIn Lnet/minecraft/inventory/Slot; L0 L1 1
    LOCALVARIABLE mouseX I L0 L1 2
    LOCALVARIABLE mouseY I L0 L1 3
    MAXSTACK = 7
    MAXLOCALS = 4

  // access flags 0x4
  protected isPointInRegion(IIIIII)Z
   L0
    LINENUMBER 670 L0
    ALOAD 0
    GETFIELD net/minecraft/client/gui/inventory/GuiContainer.guiLeft : I
    ISTORE 7
   L1
    LINENUMBER 671 L1
    ALOAD 0
    GETFIELD net/minecraft/client/gui/inventory/GuiContainer.guiTop : I
    ISTORE 8
   L2
    LINENUMBER 672 L2
    ILOAD 5
    ILOAD 7
    ISUB
    ISTORE 5
   L3
    LINENUMBER 673 L3
    ILOAD 6
    ILOAD 8
    ISUB
    ISTORE 6
   L4
    LINENUMBER 674 L4
    ILOAD 5
    ILOAD 1
    ICONST_1
    ISUB
    IF_ICMPLT L5
    ILOAD 5
    ILOAD 1
    ILOAD 3
    IADD
    ICONST_1
    IADD
    IF_ICMPGE L5
    ILOAD 6
    ILOAD 2
    ICONST_1
    ISUB
    IF_ICMPLT L5
    ILOAD 6
    ILOAD 2
    ILOAD 4
    IADD
    ICONST_1
    IADD
    IF_ICMPGE L5
    ICONST_1
    GOTO L6
   L5
   FRAME FULL [net/minecraft/client/gui/inventory/GuiContainer I I I I I I I I] []
    ICONST_0
   L6
   FRAME FULL [net/minecraft/client/gui/inventory/GuiContainer I I I I I I I I] [I]
    IRETURN
   L7
    LOCALVARIABLE this Lnet/minecraft/client/gui/inventory/GuiContainer; L0 L7 0
    LOCALVARIABLE rectX I L0 L7 1
    LOCALVARIABLE rectY I L0 L7 2
    LOCALVARIABLE rectWidth I L0 L7 3
    LOCALVARIABLE rectHeight I L0 L7 4
    LOCALVARIABLE pointX I L0 L7 5
    LOCALVARIABLE pointY I L0 L7 6
    LOCALVARIABLE i I L1 L7 7
    LOCALVARIABLE j I L2 L7 8
    MAXSTACK = 3
    MAXLOCALS = 9

  // access flags 0x4
  protected handleMouseClick(Lnet/minecraft/inventory/Slot;IILnet/minecraft/inventory/ClickType;)V
   L0
    LINENUMBER 682 L0
    ALOAD 1
    IFNULL L1
   L2
    LINENUMBER 684 L2
    ALOAD 1
    GETFIELD net/minecraft/inventory/Slot.slotNumber : I
    ISTORE 2
   L1
    LINENUMBER 687 L1
   FRAME FULL [net/minecraft/client/gui/inventory/GuiContainer net/minecraft/inventory/Slot I I net/minecraft/inventory/ClickType] []
    ALOAD 0
    GETFIELD net/minecraft/client/gui/inventory/GuiContainer.mc : Lnet/minecraft/client/Minecraft;
    GETFIELD net/minecraft/client/Minecraft.playerController : Lnet/minecraft/client/multiplayer/PlayerControllerMP;
    ALOAD 0
    GETFIELD net/minecraft/client/gui/inventory/GuiContainer.inventorySlots : Lnet/minecraft/inventory/Container;
    GETFIELD net/minecraft/inventory/Container.windowId : I
    ILOAD 2
    ILOAD 3
    ALOAD 4
    ALOAD 0
    GETFIELD net/minecraft/client/gui/inventory/GuiContainer.mc : Lnet/minecraft/client/Minecraft;
    GETFIELD net/minecraft/client/Minecraft.player : Lnet/minecraft/client/entity/EntityPlayerSP;
    INVOKEVIRTUAL net/minecraft/client/multiplayer/PlayerControllerMP.windowClick (IIILnet/minecraft/inventory/ClickType;Lnet/minecraft/entity/player/EntityPlayer;)Lnet/minecraft/item/ItemStack;
    POP
   L3
    LINENUMBER 688 L3
    RETURN
   L4
    LOCALVARIABLE this Lnet/minecraft/client/gui/inventory/GuiContainer; L0 L4 0
    LOCALVARIABLE slotIn Lnet/minecraft/inventory/Slot; L0 L4 1
    LOCALVARIABLE slotId I L0 L4 2
    LOCALVARIABLE mouseButton I L0 L4 3
    LOCALVARIABLE type Lnet/minecraft/inventory/ClickType; L0 L4 4
    MAXSTACK = 6
    MAXLOCALS = 5

  // access flags 0x4
  protected keyTyped(CI)V throws java/io/IOException 
   L0
    LINENUMBER 696 L0
    ILOAD 2
    ICONST_1
    IF_ICMPEQ L1
    ALOAD 0
    GETFIELD net/minecraft/client/gui/inventory/GuiContainer.mc : Lnet/minecraft/client/Minecraft;
    GETFIELD net/minecraft/client/Minecraft.gameSettings : Lnet/minecraft/client/settings/GameSettings;
    GETFIELD net/minecraft/client/settings/GameSettings.keyBindInventory : Lnet/minecraft/client/settings/KeyBinding;
    ILOAD 2
    INVOKEVIRTUAL net/minecraft/client/settings/KeyBinding.isActiveAndMatches (I)Z
    IFEQ L2
   L1
    LINENUMBER 698 L1
   FRAME FULL [net/minecraft/client/gui/inventory/GuiContainer I I] []
    ALOAD 0
    GETFIELD net/minecraft/client/gui/inventory/GuiContainer.mc : Lnet/minecraft/client/Minecraft;
    GETFIELD net/minecraft/client/Minecraft.player : Lnet/minecraft/client/entity/EntityPlayerSP;
    INVOKEVIRTUAL net/minecraft/client/entity/EntityPlayerSP.closeScreen ()V
   L2
    LINENUMBER 701 L2
   FRAME FULL [net/minecraft/client/gui/inventory/GuiContainer I I] []
    ALOAD 0
    ILOAD 2
    INVOKEVIRTUAL net/minecraft/client/gui/inventory/GuiContainer.checkHotbarKeys (I)Z
    POP
   L3
    LINENUMBER 703 L3
    ALOAD 0
    GETFIELD net/minecraft/client/gui/inventory/GuiContainer.theSlot : Lnet/minecraft/inventory/Slot;
    IFNULL L4
    ALOAD 0
    GETFIELD net/minecraft/client/gui/inventory/GuiContainer.theSlot : Lnet/minecraft/inventory/Slot;
    INVOKEVIRTUAL net/minecraft/inventory/Slot.getHasStack ()Z
    IFEQ L4
   L5
    LINENUMBER 705 L5
    ALOAD 0
    GETFIELD net/minecraft/client/gui/inventory/GuiContainer.mc : Lnet/minecraft/client/Minecraft;
    GETFIELD net/minecraft/client/Minecraft.gameSettings : Lnet/minecraft/client/settings/GameSettings;
    GETFIELD net/minecraft/client/settings/GameSettings.keyBindPickBlock : Lnet/minecraft/client/settings/KeyBinding;
    ILOAD 2
    INVOKEVIRTUAL net/minecraft/client/settings/KeyBinding.isActiveAndMatches (I)Z
    IFEQ L6
   L7
    LINENUMBER 707 L7
    ALOAD 0
    ALOAD 0
    GETFIELD net/minecraft/client/gui/inventory/GuiContainer.theSlot : Lnet/minecraft/inventory/Slot;
    ALOAD 0
    GETFIELD net/minecraft/client/gui/inventory/GuiContainer.theSlot : Lnet/minecraft/inventory/Slot;
    GETFIELD net/minecraft/inventory/Slot.slotNumber : I
    ICONST_0
    GETSTATIC net/minecraft/inventory/ClickType.CLONE : Lnet/minecraft/inventory/ClickType;
    INVOKEVIRTUAL net/minecraft/client/gui/inventory/GuiContainer.handleMouseClick (Lnet/minecraft/inventory/Slot;IILnet/minecraft/inventory/ClickType;)V
    GOTO L4
   L6
    LINENUMBER 709 L6
   FRAME FULL [net/minecraft/client/gui/inventory/GuiContainer I I] []
    ALOAD 0
    GETFIELD net/minecraft/client/gui/inventory/GuiContainer.mc : Lnet/minecraft/client/Minecraft;
    GETFIELD net/minecraft/client/Minecraft.gameSettings : Lnet/minecraft/client/settings/GameSettings;
    GETFIELD net/minecraft/client/settings/GameSettings.keyBindDrop : Lnet/minecraft/client/settings/KeyBinding;
    ILOAD 2
    INVOKEVIRTUAL net/minecraft/client/settings/KeyBinding.isActiveAndMatches (I)Z
    IFEQ L4
   L8
    LINENUMBER 711 L8
    ALOAD 0
    ALOAD 0
    GETFIELD net/minecraft/client/gui/inventory/GuiContainer.theSlot : Lnet/minecraft/inventory/Slot;
    ALOAD 0
    GETFIELD net/minecraft/client/gui/inventory/GuiContainer.theSlot : Lnet/minecraft/inventory/Slot;
    GETFIELD net/minecraft/inventory/Slot.slotNumber : I
    INVOKESTATIC net/minecraft/client/gui/inventory/GuiContainer.isCtrlKeyDown ()Z
    IFEQ L9
    ICONST_1
    GOTO L10
   L9
   FRAME FULL [net/minecraft/client/gui/inventory/GuiContainer I I] [net/minecraft/client/gui/inventory/GuiContainer net/minecraft/inventory/Slot I]
    ICONST_0
   L10
   FRAME FULL [net/minecraft/client/gui/inventory/GuiContainer I I] [net/minecraft/client/gui/inventory/GuiContainer net/minecraft/inventory/Slot I I]
    GETSTATIC net/minecraft/inventory/ClickType.THROW : Lnet/minecraft/inventory/ClickType;
    INVOKEVIRTUAL net/minecraft/client/gui/inventory/GuiContainer.handleMouseClick (Lnet/minecraft/inventory/Slot;IILnet/minecraft/inventory/ClickType;)V
   L4
    LINENUMBER 714 L4
   FRAME FULL [net/minecraft/client/gui/inventory/GuiContainer I I] []
    RETURN
   L11
    LOCALVARIABLE this Lnet/minecraft/client/gui/inventory/GuiContainer; L0 L11 0
    LOCALVARIABLE typedChar C L0 L11 1
    LOCALVARIABLE keyCode I L0 L11 2
    MAXSTACK = 5
    MAXLOCALS = 3

  // access flags 0x4
  protected checkHotbarKeys(I)Z
   L0
    LINENUMBER 723 L0
    ALOAD 0
    GETFIELD net/minecraft/client/gui/inventory/GuiContainer.mc : Lnet/minecraft/client/Minecraft;
    GETFIELD net/minecraft/client/Minecraft.player : Lnet/minecraft/client/entity/EntityPlayerSP;
    GETFIELD net/minecraft/client/entity/EntityPlayerSP.inventory : Lnet/minecraft/entity/player/InventoryPlayer;
    INVOKEVIRTUAL net/minecraft/entity/player/InventoryPlayer.getItemStack ()Lnet/minecraft/item/ItemStack;
    INVOKEVIRTUAL net/minecraft/item/ItemStack.isEmpty ()Z
    IFEQ L1
    ALOAD 0
    GETFIELD net/minecraft/client/gui/inventory/GuiContainer.theSlot : Lnet/minecraft/inventory/Slot;
    IFNULL L1
   L2
    LINENUMBER 725 L2
    ICONST_0
    ISTORE 2
   L3
   FRAME FULL [net/minecraft/client/gui/inventory/GuiContainer I I] []
    ILOAD 2
    BIPUSH 9
    IF_ICMPGE L1
   L4
    LINENUMBER 727 L4
    ALOAD 0
    GETFIELD net/minecraft/client/gui/inventory/GuiContainer.mc : Lnet/minecraft/client/Minecraft;
    GETFIELD net/minecraft/client/Minecraft.gameSettings : Lnet/minecraft/client/settings/GameSettings;
    GETFIELD net/minecraft/client/settings/GameSettings.keyBindsHotbar : [Lnet/minecraft/client/settings/KeyBinding;
    ILOAD 2
    AALOAD
    ILOAD 1
    INVOKEVIRTUAL net/minecraft/client/settings/KeyBinding.isActiveAndMatches (I)Z
    IFEQ L5
   L6
    LINENUMBER 729 L6
    ALOAD 0
    ALOAD 0
    GETFIELD net/minecraft/client/gui/inventory/GuiContainer.theSlot : Lnet/minecraft/inventory/Slot;
    ALOAD 0
    GETFIELD net/minecraft/client/gui/inventory/GuiContainer.theSlot : Lnet/minecraft/inventory/Slot;
    GETFIELD net/minecraft/inventory/Slot.slotNumber : I
    ILOAD 2
    GETSTATIC net/minecraft/inventory/ClickType.SWAP : Lnet/minecraft/inventory/ClickType;
    INVOKEVIRTUAL net/minecraft/client/gui/inventory/GuiContainer.handleMouseClick (Lnet/minecraft/inventory/Slot;IILnet/minecraft/inventory/ClickType;)V
   L7
    LINENUMBER 730 L7
    ICONST_1
    IRETURN
   L5
    LINENUMBER 725 L5
   FRAME FULL [net/minecraft/client/gui/inventory/GuiContainer I I] []
    IINC 2 1
    GOTO L3
   L1
    LINENUMBER 735 L1
   FRAME FULL [net/minecraft/client/gui/inventory/GuiContainer I] []
    ICONST_0
    IRETURN
   L8
    LOCALVARIABLE i I L3 L1 2
    LOCALVARIABLE this Lnet/minecraft/client/gui/inventory/GuiContainer; L0 L8 0
    LOCALVARIABLE keyCode I L0 L8 1
    MAXSTACK = 5
    MAXLOCALS = 3

  // access flags 0x1
  public onGuiClosed()V
   L0
    LINENUMBER 743 L0
    ALOAD 0
    GETFIELD net/minecraft/client/gui/inventory/GuiContainer.mc : Lnet/minecraft/client/Minecraft;
    GETFIELD net/minecraft/client/Minecraft.player : Lnet/minecraft/client/entity/EntityPlayerSP;
    IFNULL L1
   L2
    LINENUMBER 745 L2
    ALOAD 0
    GETFIELD net/minecraft/client/gui/inventory/GuiContainer.inventorySlots : Lnet/minecraft/inventory/Container;
    ALOAD 0
    GETFIELD net/minecraft/client/gui/inventory/GuiContainer.mc : Lnet/minecraft/client/Minecraft;
    GETFIELD net/minecraft/client/Minecraft.player : Lnet/minecraft/client/entity/EntityPlayerSP;
    INVOKEVIRTUAL net/minecraft/inventory/Container.onContainerClosed (Lnet/minecraft/entity/player/EntityPlayer;)V
   L1
    LINENUMBER 747 L1
   FRAME FULL [net/minecraft/client/gui/inventory/GuiContainer] []
    RETURN
   L3
    LOCALVARIABLE this Lnet/minecraft/client/gui/inventory/GuiContainer; L0 L3 0
    MAXSTACK = 2
    MAXLOCALS = 1

  // access flags 0x1
  public doesGuiPauseGame()Z
   L0
    LINENUMBER 754 L0
    ICONST_0
    IRETURN
   L1
    LOCALVARIABLE this Lnet/minecraft/client/gui/inventory/GuiContainer; L0 L1 0
    MAXSTACK = 1
    MAXLOCALS = 1

  // access flags 0x1
  public updateScreen()V
   L0
    LINENUMBER 762 L0
    ALOAD 0
    INVOKESPECIAL net/minecraft/client/gui/GuiScreen.updateScreen ()V
   L1
    LINENUMBER 764 L1
    ALOAD 0
    GETFIELD net/minecraft/client/gui/inventory/GuiContainer.mc : Lnet/minecraft/client/Minecraft;
    GETFIELD net/minecraft/client/Minecraft.player : Lnet/minecraft/client/entity/EntityPlayerSP;
    INVOKEVIRTUAL net/minecraft/client/entity/EntityPlayerSP.isEntityAlive ()Z
    IFEQ L2
    ALOAD 0
    GETFIELD net/minecraft/client/gui/inventory/GuiContainer.mc : Lnet/minecraft/client/Minecraft;
    GETFIELD net/minecraft/client/Minecraft.player : Lnet/minecraft/client/entity/EntityPlayerSP;
    GETFIELD net/minecraft/client/entity/EntityPlayerSP.isDead : Z
    IFEQ L3
   L2
    LINENUMBER 766 L2
   FRAME FULL [net/minecraft/client/gui/inventory/GuiContainer] []
    ALOAD 0
    GETFIELD net/minecraft/client/gui/inventory/GuiContainer.mc : Lnet/minecraft/client/Minecraft;
    GETFIELD net/minecraft/client/Minecraft.player : Lnet/minecraft/client/entity/EntityPlayerSP;
    INVOKEVIRTUAL net/minecraft/client/entity/EntityPlayerSP.closeScreen ()V
   L3
    LINENUMBER 768 L3
   FRAME FULL [net/minecraft/client/gui/inventory/GuiContainer] []
    RETURN
   L4
    LOCALVARIABLE this Lnet/minecraft/client/gui/inventory/GuiContainer; L0 L4 0
    MAXSTACK = 1
    MAXLOCALS = 1

  // access flags 0x1
  public getSlotUnderMouse()Lnet/minecraft/inventory/Slot;
  @Ljavax/annotation/Nullable;()
   L0
    LINENUMBER 776 L0
    ALOAD 0
    GETFIELD net/minecraft/client/gui/inventory/GuiContainer.theSlot : Lnet/minecraft/inventory/Slot;
    ARETURN
   L1
    LOCALVARIABLE this Lnet/minecraft/client/gui/inventory/GuiContainer; L0 L1 0
    MAXSTACK = 1
    MAXLOCALS = 1

  // access flags 0x1
  public getGuiLeft()I
   L0
    LINENUMBER 777 L0
    ALOAD 0
    GETFIELD net/minecraft/client/gui/inventory/GuiContainer.guiLeft : I
    IRETURN
   L1
    LOCALVARIABLE this Lnet/minecraft/client/gui/inventory/GuiContainer; L0 L1 0
    MAXSTACK = 1
    MAXLOCALS = 1

  // access flags 0x1
  public getGuiTop()I
   L0
    LINENUMBER 778 L0
    ALOAD 0
    GETFIELD net/minecraft/client/gui/inventory/GuiContainer.guiTop : I
    IRETURN
   L1
    LOCALVARIABLE this Lnet/minecraft/client/gui/inventory/GuiContainer; L0 L1 0
    MAXSTACK = 1
    MAXLOCALS = 1

  // access flags 0x1
  public getXSize()I
   L0
    LINENUMBER 779 L0
    ALOAD 0
    GETFIELD net/minecraft/client/gui/inventory/GuiContainer.xSize : I
    IRETURN
   L1
    LOCALVARIABLE this Lnet/minecraft/client/gui/inventory/GuiContainer; L0 L1 0
    MAXSTACK = 1
    MAXLOCALS = 1

  // access flags 0x1
  public getYSize()I
   L0
    LINENUMBER 780 L0
    ALOAD 0
    GETFIELD net/minecraft/client/gui/inventory/GuiContainer.ySize : I
    IRETURN
   L1
    LOCALVARIABLE this Lnet/minecraft/client/gui/inventory/GuiContainer; L0 L1 0
    MAXSTACK = 1
    MAXLOCALS = 1

  // access flags 0x8
  static <clinit>()V
   L0
    LINENUMBER 29 L0
    NEW net/minecraft/util/ResourceLocation
    DUP
    LDC "textures/gui/container/inventory.png"
    INVOKESPECIAL net/minecraft/util/ResourceLocation.<init> (Ljava/lang/String;)V
    PUTSTATIC net/minecraft/client/gui/inventory/GuiContainer.INVENTORY_BACKGROUND : Lnet/minecraft/util/ResourceLocation;
    RETURN
    MAXSTACK = 3
    MAXLOCALS = 0
}
